<?xml version="1.0" encoding="UTF-8"?>
<countries>
  <country>
    <countryId>AD</countryId>
    <names>
      <name><languageId>de</languageId><name>Andorra</name></name>
      <name><languageId>en</languageId><name>Andorra</name></name>
      <name><languageId>es</languageId><name>Andorra</name></name>
    </names>
    <locales>
      <locale><localeId>ca_AD.UTF-8</localeId><rank>1000</rank></locale>
    </locales>
    <languages>
      <language><languageId>ca</languageId><rank>1000</rank></language>
    </languages>
    <keyboards>
      <keyboard><keyboardId>es(cat)</keyboardId><rank>1000</rank></keyboard>
      <keyboard><keyboardId>ad</keyboardId><rank>0</rank></keyboard>
    </keyboards>
    <timezones>
      <timezone><timezoneId>Europe/Andorra</timezoneId><rank>1000</rank></timezone>
    </timezones>
  </country>
  <country>
    <countryId>AE</countryId>
    <names>
      <name><languageId>ar</languageId><name>الإمارات العربية المتحدة</name></name>
      <name><languageId>de</languageId><name>Vereinigte Arabische Emirate</name></name>
      <name><languageId>en</languageId><name>United Arab Emirates</name></name>
    </names>
    <locales>
      <locale><localeId>ar_AE.UTF-8</localeId><rank>1000</rank></locale>
    </locales>
    <languages>
      <language><languageId>ar</languageId><rank>1000</rank></language>
    </languages>
    <keyboards>
      <keyboard><keyboardId>ara</keyboardId><rank>1000</rank></keyboard>
    </keyboards>
    <timezones>
      <timezone><timezoneId>Asia/Dubai</timezoneId><rank>1000</rank></timezone>
    </timezones>
  </country>
  <country>
    <countryId>AL</countryId>
    <names>
      <name><languageId>de</languageId><name>Mazedonien</name></name>
      <name><languageId>en</languageId><name>Macedonia</name></name>
      <name><languageId>sq</languageId><name>Македонија</name></name>
    </names>
    <locales>
      <locale><localeId>sq_AL.UTF-8</localeId><rank>100</rank></locale>
    </locales>
    <languages>
      <language><languageId>sq</languageId><rank>1000</rank></language>
    </languages>
    <keyboards>
      <keyboard><keyboardId>al</keyboardId><rank>1000</rank></keyboard>
    </keyboards>
    <timezones>
      <timezone><timezoneId>Europe/Tirane</timezoneId><rank>1000</rank></timezone>
    </timezones>
  </country>
  <country>
    <countryId>AT</countryId>
    <names>
      <name><languageId>de</languageId><name>Österreich</name></name>
      <name><languageId>en</languageId><name>Austria</name></name>
    </names>
    <locales>
      <locale><localeId>de_AT.UTF-8</localeId><rank>1000</rank></locale>
    </locales>
    <languages>
      <language><languageId>de</languageId><rank>1000</rank></language>
    </languages>
    <keyboards>
      <keyboard><keyboardId>at(nodeadkeys)</keyboardId><rank>1000</rank></keyboard>
    </keyboards>
    <timezones>
      <timezone><timezoneId>Europe/Vienna</timezoneId><rank>1000</rank></timezone>
    </timezones>
  </country>
  <country>
    <countryId>BD</countryId>
    <names>
      <name><languageId>de</languageId><name>Bangladesh</name></name>
      <name><languageId>en</languageId><name>Bangladesh</name></name>
    </names>
    <locales>
      <locale><localeId>bn_BD.UTF-8</localeId><rank>1000</rank></locale>
    </locales>
    <languages>
      <language><languageId>bn</languageId><rank>990</rank></language>
      <language><languageId>en</languageId><rank>10</rank></language>
    </languages>
    <keyboards>
      <keyboard><keyboardId>us</keyboardId><rank>1000</rank></keyboard>
    </keyboards>
    <timezones>
      <timezone><timezoneId>Asia/Dhaka</timezoneId><rank>1000</rank></timezone>
    </timezones>
  </country>
  <country>
    <countryId>BE</countryId>
    <names>
      <name><languageId>de</languageId><name>Belgien</name></name>
      <name><languageId>en</languageId><name>Belgium</name></name>
    </names>
    <locales>
      <locale><localeId>nl_BE.UTF-8</localeId><rank>590</rank></locale>
      <locale><localeId>fr_BE.UTF-8</localeId><rank>400</rank></locale>
      <locale><localeId>de_BE.UTF-8</localeId><rank>5</rank></locale>
      <locale><localeId>wa_BE.UTF-8</localeId><rank>2</rank></locale>
      <locale><localeId>li_BE.UTF-8</localeId><rank>1</rank></locale>
    </locales>
    <languages>
      <language><languageId>nl</languageId><rank>590</rank></language>
      <language><languageId>fr</languageId><rank>400</rank></language>
      <language><languageId>de</languageId><rank>5</rank></language>
      <language><languageId>wa</languageId><rank>2</rank></language>
      <language><languageId>li</languageId><rank>1</rank></language>
    </languages>
    <keyboards>
      <keyboard><keyboardId>be(oss)</keyboardId><rank>900</rank></keyboard>
      <keyboard><keyboardId>be</keyboardId><rank>0</rank></keyboard>
    </keyboards>
    <timezones>
      <timezone><timezoneId>Europe/Brussels</timezoneId><rank>1000</rank></timezone>
    </timezones>
  </country>
  <country>
    <countryId>BH</countryId>
    <names>
      <name><languageId>de</languageId><name>Bahrain</name></name>
      <name><languageId>en</languageId><name>Bahrain</name></name>
    </names>
    <locales>
      <locale><localeId>ar_BH.UTF-8</localeId><rank>1000</rank></locale>
    </locales>
    <languages>
      <language><languageId>ar</languageId><rank>1000</rank></language>
    </languages>
    <keyboards>
      <keyboard><keyboardId>ara</keyboardId><rank>1000</rank></keyboard>
    </keyboards>
    <timezones>
      <timezone><timezoneId>Asia/Bahrain</timezoneId><rank>1000</rank></timezone>
    </timezones>
  </country>
  <country>
    <countryId>BY</countryId>
    <names>
      <name><languageId>de</languageId><name>Belarus</name></name>
      <name><languageId>de_CH</languageId><name>Weissrussland</name></name>
      <name><languageId>en</languageId><name>Belarus</name></name>
    </names>
    <locales>
      <locale><localeId>be_BY.UTF-8</localeId><rank>980</rank></locale>
      <locale><localeId>be_BY.UTF-8@latin</localeId><rank>20</rank></locale>
    </locales>
    <languages>
      <language><languageId>ru</languageId><rank>720</rank></language>
      <language><languageId>be</languageId><rank>120</rank></language>
    </languages>
    <keyboards>
      <keyboard><keyboardId>by</keyboardId><rank>950</rank></keyboard>
      <keyboard><keyboardId>by(latin)</keyboardId><rank>0</rank></keyboard>
      <keyboard><keyboardId>by(legacy)</keyboardId><rank>0</rank></keyboard>
    </keyboards>
    <timezones>
      <timezone><timezoneId>Europe/Minsk</timezoneId><rank>1000</rank></timezone>
    </timezones>
  </country>
  <country>
    <countryId>CH</countryId>
    <names>
      <name><languageId>de</languageId><name>Schweiz</name></name>
      <name><languageId>en</languageId><name>Switzerland</name></name>
    </names>
    <locales>
      <locale><localeId>de_CH.UTF-8</localeId><rank>637</rank></locale>
      <locale><localeId>fr_CH.UTF-8</localeId><rank>204</rank></locale>
      <locale><localeId>it_CH.UTF-8</localeId><rank>65</rank></locale>
      <locale><localeId>wae_CH.UTF-8</localeId><rank>1</rank></locale>
    </locales>
    <languages>
      <language><languageId>de</languageId><rank>637</rank></language>
      <language><languageId>fr</languageId><rank>204</rank></language>
      <language><languageId>it</languageId><rank>65</rank></language>
      <language><languageId>rm</languageId><rank>10</rank></language>
      <language><languageId>wae</languageId><rank>1</rank></language>
    </languages>
    <keyboards>
      <keyboard><keyboardId>ch</keyboardId><rank>700</rank></keyboard>
      <keyboard><keyboardId>ch(fr)</keyboardId><rank>200</rank></keyboard>
      <keyboard><keyboardId>it</keyboardId><rank>100</rank></keyboard>
    </keyboards>
    <timezones>
      <timezone><timezoneId>Europe/Zurich</timezoneId><rank>1000</rank></timezone>
    </timezones>
  </country>
  <country>
    <countryId>CN</countryId>
    <names>
      <name><languageId>de</languageId><name>China</name></name>
      <name><languageId>en</languageId><name>China</name></name>
      <name><languageId>zh</languageId><name>中国</name></name>
      <name><languageId>zh_Hant</languageId><name>中華人民共和國</name></name>
    </names>
    <locales>
      <locale><localeId>zh_CN.UTF-8</localeId><rank>1000</rank></locale>
    </locales>
    <languages>
      <language><languageId>zh</languageId><rank>1000</rank></language>
    </languages>
    <keyboards>
      <keyboard><keyboardId>cn</keyboardId><rank>1000</rank></keyboard>
    </keyboards>
    <timezones>
      <timezone><timezoneId>Asia/Shanghai</timezoneId><rank>1000</rank></timezone>
    </timezones>
  </country>
  <country>
    <countryId>CY</countryId>
    <names>
      <name><languageId>de</languageId><name>Zypern</name></name>
      <name><languageId>el</languageId><name>Κύπρος</name></name>
      <name><languageId>en</languageId><name>Cyprus</name></name>
    </names>
    <locales>
      <locale><localeId>el_CY.UTF-8</localeId><rank>1000</rank></locale>
    </locales>
    <languages>
      <language><languageId>el</languageId><rank>1000</rank></language>
    </languages>
    <keyboards>
      <keyboard><keyboardId>gr</keyboardId><rank>1000</rank></keyboard>
    </keyboards>
    <timezones>
      <timezone><timezoneId>Asia/Nicosia</timezoneId><rank>1000</rank></timezone>
    </timezones>
  </country>
  <country>
    <countryId>CZ</countryId>
    <names>
      <name><languageId>cs</languageId><name>Tjekkiet</name></name>
      <name><languageId>de</languageId><name>Tschechische Republik</name></name>
      <name><languageId>en</languageId><name>Czech Republic</name></name>
    </names>
    <locales>
      <locale><localeId>cs_CZ.UTF-8</localeId><rank>1000</rank></locale>
    </locales>
    <languages>
      <language><languageId>ca</languageId><rank>1000</rank></language>
    </languages>
    <keyboards>
      <keyboard><keyboardId>cz</keyboardId><rank>1000</rank></keyboard>
    </keyboards>
    <timezones>
      <timezone><timezoneId>Europe/Prague</timezoneId><rank>1000</rank></timezone>
    </timezones>
  </country>
  <country>
    <countryId>DE</countryId>
    <names>
      <name><languageId>de</languageId><name>Deutschland</name></name>
      <name><languageId>en</languageId><name>Germany</name></name>
    </names>
    <locales>
      <locale><localeId>de_DE.UTF-8</localeId><rank>950</rank></locale>
      <locale><localeId>nds_DE.UTF-8</localeId><rank>11</rank></locale>
      <locale><localeId>hsb_DE.UTF-8</localeId><rank>10</rank></locale>
      <locale><localeId>fy_DE.UTF-8</localeId><rank>9</rank></locale>
    </locales>
    <languages>
      <language><languageId>de</languageId><rank>950</rank></language>
      <language><languageId>nds</languageId><rank>11</rank></language>
      <language><languageId>hsb</languageId><rank>10</rank></language>
      <language><languageId>fy</languageId><rank>9</rank></language>
    </languages>
    <keyboards>
      <keyboard><keyboardId>de(nodeadkeys)</keyboardId><rank>900</rank></keyboard>
      <keyboard><keyboardId>de(deadacute)</keyboardId><rank>100</rank></keyboard>
    </keyboards>
    <timezones>
      <timezone><timezoneId>Europe/Berlin</timezoneId><rank>1000</rank></timezone>
    </timezones>
  </country>
  <country>
    <countryId>DK</countryId>
    <names>
      <name><languageId>da</languageId><name>Danmark</name></name>
      <name><languageId>de</languageId><name>Dänemark</name></name>
      <name><languageId>en</languageId><name>Denmark</name></name>
    </names>
    <locales>
      <locale><localeId>da_DK.UTF-8</localeId><rank>950</rank></locale>
      <locale><localeId>en_DK.UTF-8</localeId><rank>50</rank></locale>
    </locales>
    <languages>
      <language><languageId>da</languageId><rank>999</rank></language>
      <language><languageId>en</languageId><rank>1</rank></language>
    </languages>
    <keyboards>
      <keyboard><keyboardId>dk</keyboardId><rank>1000</rank></keyboard>
    </keyboards>
    <timezones>
      <timezone><timezoneId>Europe/Copenhagen</timezoneId><rank>1000</rank></timezone>
    </timezones>
  </country>
  <country>
    <countryId>DZ</countryId>
    <names>
      <name><languageId>de</languageId><name>Algerien</name></name>
      <name><languageId>en</languageId><name>Algeria</name></name>
    </names>
    <locales>
      <locale><localeId>ar_DZ.UTF-8</localeId><rank>1000</rank></locale>
    </locales>
    <languages>
      <language><languageId>ar</languageId><rank>1000</rank></language>
    </languages>
    <keyboards>
      <keyboard><keyboardId>ara(azerty)</keyboardId><rank>1000</rank></keyboard>
    </keyboards>
    <timezones>
      <timezone><timezoneId>Africa/Algiers</timezoneId><rank>1000</rank></timezone>
    </timezones>
  </country>
  <country>
    <countryId>EE</countryId>
    <names>
      <name><languageId>de</languageId><name>Estland</name></name>
      <name><languageId>en</languageId><name>Estonia</name></name>
      <name><languageId>et</languageId><name>Eesti</name></name>
    </names>
    <locales>
      <locale><localeId>et_EE.UTF-8</localeId><rank>1000</rank></locale>
    </locales>
    <languages>
      <language><languageId>et</languageId><rank>1000</rank></language>
    </languages>
    <keyboards>
      <keyboard><keyboardId>ee</keyboardId><rank>1000</rank></keyboard>
    </keyboards>
    <timezones>
      <timezone><timezoneId>Europe/Tallinn</timezoneId><rank>1000</rank></timezone>
    </timezones>
  </country>
  <country>
    <countryId>EG</countryId>
    <names>
      <name><languageId>de</languageId><name>Ägypten</name></name>
      <name><languageId>en</languageId><name>Egypt</name></name>
    </names>
    <locales>
      <locale><localeId>ar_EG.UTF-8</localeId><rank>1000</rank></locale>
    </locales>
    <languages>
      <language><languageId>ar</languageId><rank>1000</rank></language>
    </languages>
    <keyboards>
      <keyboard><keyboardId>ara</keyboardId><rank>1000</rank></keyboard>
    </keyboards>
    <timezones>
      <timezone><timezoneId>Africa/Cairo</timezoneId><rank>1000</rank></timezone>
    </timezones>
  </country>
  <country>
    <countryId>ES</countryId>
    <names>
      <name><languageId>de</languageId><name>Spanien</name></name>
      <name><languageId>en</languageId><name>Spain</name></name>
    </names>
    <locales>
      <locale><localeId>es_ES.UTF-8</localeId><rank>700</rank></locale>
      <locale><localeId>an_ES.UTF-8</localeId><rank>150</rank></locale>
      <locale><localeId>ca_ES.UTF-8</localeId><rank>100</rank></locale>
      <locale><localeId>ast_ES.UTF-8</localeId><rank>90</rank></locale>
      <locale><localeId>gl_ES.UTF-8</localeId><rank>80</rank></locale>
      <locale><localeId>eu_ES.UTF-8</localeId><rank>70</rank></locale>
    </locales>
    <languages>
      <language><languageId>es</languageId><rank>700</rank></language>
      <language><languageId>an</languageId><rank>150</rank></language>
      <language><languageId>ca</languageId><rank>100</rank></language>
      <language><languageId>ast</languageId><rank>90</rank></language>
      <language><languageId>gl</languageId><rank>80</rank></language>
      <language><languageId>eu</languageId><rank>70</rank></language>
    </languages>
    <keyboards>
      <keyboard><keyboardId>es</keyboardId><rank>1000</rank></keyboard>
    </keyboards>
    <timezones>
      <timezone><timezoneId>[Europe/Madrid</timezoneId><rank>1000</rank></timezone>
    </timezones>
  </country>
  <country>
    <countryId>FI</countryId>
    <names>
      <name><languageId>de</languageId><name>Finnland</name></name>
      <name><languageId>en</languageId><name>Finland</name></name>
      <name><languageId>fi</languageId><name>Suomi</name></name>
    </names>
    <locales>
      <locale><localeId>fi_FI.UTF-8</localeId><rank>900</rank></locale>
      <locale><localeId>sv_FI.UTF-8</localeId><rank>100</rank></locale>
    </locales>
    <languages>
      <language><languageId>fi</languageId><rank>900</rank></language>
      <language><languageId>sv</languageId><rank>100</rank></language>
    </languages>
    <keyboards>
      <keyboard><keyboardId>fi</keyboardId><rank>900</rank></keyboard>
      <keyboard><keyboardId>fi(nodeadkeys)</keyboardId><rank>100</rank></keyboard>
    </keyboards>
    <timezones>
      <timezone><timezoneId>Europe/Helsinki</timezoneId><rank>1000</rank></timezone>
    </timezones>
  </country>
  <country>
    <countryId>FR</countryId>
    <names>
      <name><languageId>de</languageId><name>Frankreich</name></name>
      <name><languageId>en</languageId><name>France</name></name>
    </names>
    <locales>
      <locale><localeId>fr_FR.UTF-8</localeId><rank>950</rank></locale>
      <locale><localeId>br_FR.UTF-8</localeId><rank>11</rank></locale>
      <locale><localeId>oc_FR.UTF-8</localeId><rank>10</rank></locale>
      <locale><localeId>ca_FR.UTF-8</localeId><rank>9</rank></locale>
    </locales>
    <languages>
      <language><languageId>fr</languageId><rank>950</rank></language>
      <language><languageId>br</languageId><rank>11</rank></language>
      <language><languageId>oc</languageId><rank>10</rank></language>
      <language><languageId>ca</languageId><rank>9</rank></language>
    </languages>
    <keyboards>
      <keyboard><keyboardId>fr(oss)</keyboardId><rank>900</rank></keyboard>
      <keyboard><keyboardId>fr</keyboardId><rank>0</rank></keyboard>
      <keyboard><keyboardId>fr(latin9)</keyboardId><rank>0</rank></keyboard>
    </keyboards>
    <timezones>
      <timezone><timezoneId>Europe/Paris</timezoneId><rank>1000</rank></timezone>
    </timezones>
  </country>
  <country>
    <countryId>GB</countryId>
    <names>
      <name><languageId>cy</languageId><name>Prydain Fawr</name></name>
      <name><languageId>de</languageId><name>Vereinigtes Königreich</name></name>
      <name><languageId>en</languageId><name>United Kingdom</name></name>
    </names>
    <locales>
      <locale><localeId>en_GB.UTF-8</localeId><rank>900</rank></locale>
      <locale><localeId>cy_GB.UTF-8</localeId><rank>20</rank></locale>
      <locale><localeId>gd_GB.UTF-8</localeId><rank>15</rank></locale>
      <locale><localeId>kw_GB.UTF-8</localeId><rank>10</rank></locale>
      <locale><localeId>gv_GB.UTF-8</localeId><rank>1</rank></locale>
    </locales>
    <languages>
      <language><languageId>en</languageId><rank>900</rank></language>
      <language><languageId>cy</languageId><rank>20</rank></language>
      <language><languageId>gd</languageId><rank>15</rank></language>
      <language><languageId>kw</languageId><rank>10</rank></language>
      <language><languageId>gv</languageId><rank>1</rank></language>
    </languages>
    <keyboards>
      <keyboard><keyboardId>gb</keyboardId><rank>1000</rank></keyboard>
    </keyboards>
    <timezones>
      <timezone><timezoneId>Europe/London</timezoneId><rank>1000</rank></timezone>
    </timezones>
  </country>
  <country>
    <countryId>GR</countryId>
    <names>
      <name><languageId>de</languageId><name>Griechenland</name></name>
      <name><languageId>el</languageId><name>Ελλάδα</name></name>
      <name><languageId>en</languageId><name>Greece</name></name>
    </names>
    <locales>
      <locale><localeId>el_GR.UTF-8</localeId><rank>1000</rank></locale>
    </locales>
    <languages>
      <language><languageId>el</languageId><rank>1000</rank></language>
    </languages>
    <keyboards>
      <keyboard><keyboardId>gr</keyboardId><rank>1000</rank></keyboard>
    </keyboards>
    <timezones>
      <timezone><timezoneId>Europe/Athens</timezoneId><rank>1000</rank></timezone>
    </timezones>
  </country>
  <country>
    <countryId>HK</countryId>
    <names>
      <name><languageId>de</languageId><name>Hong Kong</name></name>
      <name><languageId>en</languageId><name>Hong Kong</name></name>
      <name><languageId>zh</languageId><name>中国香港特别行政区</name></name>
      <name><languageId>zh_Hant</languageId><name>中華人民共和國香港特別行政區</name></name>
    </names>
    <locales>
      <locale><localeId>zh_HK.UTF-8</localeId><rank>1000</rank></locale>
    </locales>
    <languages>
      <language><languageId>zh</languageId><rank>1000</rank></language>
    </languages>
    <keyboards>
      <keyboard><keyboardId>cn</keyboardId><rank>1000</rank></keyboard>
    </keyboards>
    <timezones>
      <timezone><timezoneId>Asia/Hong_Kong</timezoneId><rank>1000</rank></timezone>
    </timezones>
  </country>
  <country>
    <countryId>HR</countryId>
    <names>
      <name><languageId>de</languageId><name>Kroatien</name></name>
      <name><languageId>en</languageId><name>Croatia</name></name>
      <name><languageId>hr</languageId><name>Hrvatska</name></name>
    </names>
    <locales>
      <locale><localeId>hr_HR.UTF-8</localeId><rank>1000</rank></locale>
    </locales>
    <languages>
      <language><languageId>hr</languageId><rank>1000</rank></language>
    </languages>
    <keyboards>
      <keyboard><keyboardId>hr</keyboardId><rank>1000</rank></keyboard>
    </keyboards>
    <timezones>
      <timezone><timezoneId>Europe/Zagreb</timezoneId><rank>1000</rank></timezone>
    </timezones>
  </country>
  <country>
    <countryId>HU</countryId>
    <names>
      <name><languageId>de</languageId><name>Ungarn</name></name>
      <name><languageId>en</languageId><name>Hungary</name></name>
      <name><languageId>hu</languageId><name>Magyarország</name></name>
    </names>
    <locales>
      <locale><localeId>hu_HU.UTF-8</localeId><rank>1000</rank></locale>
    </locales>
    <languages>
      <language><languageId>hu</languageId><rank>1000</rank></language>
    </languages>
    <keyboards>
      <keyboard><keyboardId>hu</keyboardId><rank>1000</rank></keyboard>
    </keyboards>
    <timezones>
      <timezone><timezoneId>Europe/Budapest</timezoneId><rank>1000</rank></timezone>
    </timezones>
  </country>
  <country>
    <countryId>ID</countryId>
    <names>
      <name><languageId>de</languageId><name>Indonesien</name></name>
      <name><languageId>en</languageId><name>Indonesia</name></name>
      <name><languageId>id</languageId><name>Indonesia</name></name>
    </names>
    <locales>
      <locale><localeId>id_ID.UTF-8</localeId><rank>1000</rank></locale>
    </locales>
    <languages>
      <language><languageId>id</languageId><rank>1000</rank></language>
    </languages>
    <keyboards>
      <keyboard><keyboardId>us</keyboardId><rank>1000</rank></keyboard>
    </keyboards>
    <timezones>
      <timezone><timezoneId>Asia/Jayapura</timezoneId><rank>1000</rank></timezone>
    </timezones>
  </country>
  <country>
    <countryId>IN</countryId>
    <names>
      <name><languageId>de</languageId><name>Indien</name></name>
      <name><languageId>en</languageId><name>India</name></name>
    </names>
    <locales>
      <locale><localeId>hi_IN.UTF-8</localeId><rank>400</rank></locale>
      <locale><localeId>en_IN.UTF-8</localeId><rank>200</rank></locale>
      <locale><localeId>bn_IN.UTF-8</localeId><rank>150</rank></locale>
      <locale><localeId>te_IN.UTF-8</localeId><rank>140</rank></locale>
      <locale><localeId>mr_IN.UTF-8</localeId><rank>130</rank></locale>
      <locale><localeId>ta_IN.UTF-8</localeId><rank>120</rank></locale>
      <locale><localeId>ur_IN.UTF-8</localeId><rank>110</rank></locale>
      <locale><localeId>gu_IN.UTF-8</localeId><rank>100</rank></locale>
      <locale><localeId>kn_IN.UTF-8</localeId><rank>90</rank></locale>
      <locale><localeId>ml_IN.UTF-8</localeId><rank>85</rank></locale>
      <locale><localeId>or_IN.UTF-8</localeId><rank>80</rank></locale>
      <locale><localeId>pa_IN.UTF-8</localeId><rank>75</rank></locale>
      <locale><localeId>as_IN.UTF-8</localeId><rank>70</rank></locale>
      <locale><localeId>mai_IN.UTF-8</localeId><rank>65</rank></locale>
      <locale><localeId>sat_IN.UTF-8</localeId><rank>60</rank></locale>
      <locale><localeId>ks_IN.UTF-8</localeId><rank>55</rank></locale>
      <locale><localeId>ks_IN.UTF-8@devanagari</localeId><rank>50</rank></locale>
      <locale><localeId>kok_IN.UTF-8</localeId><rank>45</rank></locale>
      <locale><localeId>sd_IN.UTF-8</localeId><rank>40</rank></locale>
      <locale><localeId>sd_IN.UTF-8@devanagari</localeId><rank>35</rank></locale>
      <locale><localeId>doi_IN.UTF-8</localeId><rank>30</rank></locale>
      <locale><localeId>mni_IN.UTF-8</localeId><rank>25</rank></locale>
      <locale><localeId>brx_IN.UTF-8</localeId><rank>20</rank></locale>
      <locale><localeId>bho_IN.UTF-8</localeId><rank>6</rank></locale>
      <locale><localeId>bo_IN.UTF-8</localeId><rank>5</rank></locale>
      <locale><localeId>hne_IN.UTF-8</localeId><rank>4</rank></locale>
      <locale><localeId>mag_IN.UTF-8</localeId><rank>3</rank></locale>
      <locale><localeId>ar_IN.UTF-8</localeId><rank>2</rank></locale>
      <locale><localeId>sa_IN.UTF-8</localeId><rank>0</rank></locale>
    </locales>
    <languages>
      <language><languageId>hi</languageId><rank>400</rank></language>
      <language><languageId>en</languageId><rank>200</rank></language>
      <language><languageId>bn</languageId><rank>150</rank></language>
      <language><languageId>te</languageId><rank>140</rank></language>
      <language><languageId>mr</languageId><rank>130</rank></language>
      <language><languageId>ta</languageId><rank>120</rank></language>
      <language><languageId>ur</languageId><rank>110</rank></language>
      <language><languageId>gu</languageId><rank>100</rank></language>
      <language><languageId>kn</languageId><rank>90</rank></language>
      <language><languageId>ml</languageId><rank>85</rank></language>
      <language><languageId>or</languageId><rank>80</rank></language>
      <language><languageId>pa</languageId><rank>75</rank></language>
      <language><languageId>as</languageId><rank>70</rank></language>
      <language><languageId>mai</languageId><rank>65</rank></language>
      <language><languageId>sat</languageId><rank>60</rank></language>
      <language><languageId>ks</languageId><rank>55</rank></language>
      <language><languageId>kok</languageId><rank>45</rank></language>
      <language><languageId>sd</languageId><rank>40</rank></language>
      <language><languageId>doi</languageId><rank>30</rank></language>
      <language><languageId>mni</languageId><rank>25</rank></language>
      <language><languageId>brx</languageId><rank>20</rank></language>
      <language><languageId>bho</languageId><rank>6</rank></language>
      <language><languageId>bo</languageId><rank>5</rank></language>
      <language><languageId>hne</languageId><rank>4</rank></language>
      <language><languageId>mag</languageId><rank>3</rank></language>
      <language><languageId>ar</languageId><rank>2</rank></language>
      <language><languageId>ne</languageId><rank>1</rank></language>
      <language><languageId>sa</languageId><rank>0</rank></language>
    </languages>
    <keyboards>
      <keyboard><keyboardId>us</keyboardId><rank>950</rank></keyboard>
    </keyboards>
    <timezones>
      <timezone><timezoneId>Asia/Kolkata</timezoneId><rank>1000</rank></timezone>
    </timezones>
  </country>
  <country>
    <countryId>IQ</countryId>
    <names>
      <name><languageId>de</languageId><name>Irak</name></name>
      <name><languageId>en</languageId><name>Iraq</name></name>
    </names>
    <locales>
      <locale><localeId>ar_IQ.UTF-8</localeId><rank>1000</rank></locale>
    </locales>
    <languages>
      <language><languageId>ar</languageId><rank>1000</rank></language>
    </languages>
    <keyboards>
      <keyboard><keyboardId>ara</keyboardId><rank>1000</rank></keyboard>
    </keyboards>
    <timezones>
      <timezone><timezoneId>Asia/Baghdad</timezoneId><rank>1000</rank></timezone>
    </timezones>
  </country>
  <country>
    <countryId>IS</countryId>
    <names>
      <name><languageId>de</languageId><name>Island</name></name>
      <name><languageId>en</languageId><name>Iceland</name></name>
      <name><languageId>is</languageId><name>Ísland</name></name>
    </names>
    <locales>
      <locale><localeId>is_IS.UTF-8</localeId><rank>1000</rank></locale>
    </locales>
    <languages>
      <language><languageId>is</languageId><rank>1000</rank></language>
    </languages>
    <keyboards>
      <keyboard><keyboardId>is</keyboardId><rank>1000</rank></keyboard>
    </keyboards>
    <timezones>
      <timezone><timezoneId>Atlantic/Reykjavik</timezoneId><rank>1000</rank></timezone>
    </timezones>
  </country>
  <country>
    <countryId>IT</countryId>
    <names>
      <name><languageId>de</languageId><name>Italien</name></name>
      <name><languageId>en</languageId><name>Italy</name></name>
      <name><languageId>es</languageId><name>Italia</name></name>
    </names>
    <locales>
      <locale><localeId>it_IT.UTF-8</localeId><rank>950</rank></locale>
      <locale><localeId>lij_IT.UTF-8</localeId><rank>20</rank></locale>
      <locale><localeId>sc_IT.UTF-8</localeId><rank>15</rank></locale>
      <locale><localeId>fur_IT.UTF-8</localeId><rank>10</rank></locale>
      <locale><localeId>ca_IT.UTF-8</localeId><rank>1</rank></locale>
    </locales>
    <languages>
      <language><languageId>it</languageId><rank>950</rank></language>
      <language><languageId>lij</languageId><rank>20</rank></language>
      <language><languageId>sc</languageId><rank>15</rank></language>
      <language><languageId>fur</languageId><rank>10</rank></language>
      <language><languageId>ca</languageId><rank>1</rank></language>
    </languages>
    <keyboards>
      <keyboard><keyboardId>it</keyboardId><rank>1000</rank></keyboard>
    </keyboards>
    <timezones>
      <timezone><timezoneId>Europe/Rome</timezoneId><rank>1000</rank></timezone>
    </timezones>
  </country>
  <country>
    <countryId>JO</countryId>
    <names>
      <name><languageId>de</languageId><name>Jordanien</name></name>
      <name><languageId>en</languageId><name>Jordan</name></name>
    </names>
    <locales>
      <locale><localeId>ar_JO.UTF-8</localeId><rank>1000</rank></locale>
    </locales>
    <languages>
      <language><languageId>ar</languageId><rank>1000</rank></language>
    </languages>
    <keyboards>
      <keyboard><keyboardId>ara</keyboardId><rank>1000</rank></keyboard>
    </keyboards>
    <timezones>
      <timezone><timezoneId>Asia/Amman</timezoneId><rank>1000</rank></timezone>
    </timezones>
  </country>
  <country>
    <countryId>JP</countryId>
    <names>
      <name><languageId>de</languageId><name>Japan</name></name>
      <name><languageId>en</languageId><name>Japan</name></name>
    </names>
    <locales>
      <locale><localeId>ja_JP.UTF-8</localeId><rank>1000</rank></locale>
    </locales>
    <languages>
      <language><languageId>ja</languageId><rank>1000</rank></language>
    </languages>
    <keyboards>
      <keyboard><keyboardId>jp</keyboardId><rank>1000</rank></keyboard>
    </keyboards>
    <timezones>
      <timezone><timezoneId>Asia/Tokyo</timezoneId><rank>1000</rank></timezone>
    </timezones>
  </country>
  <country>
    <countryId>KR</countryId>
    <names>
      <name><languageId>de</languageId><name>Republik Korea</name></name>
      <name><languageId>en</languageId><name>South Korea</name></name>
      <name><languageId>ko</languageId><name>대한민국</name></name>
    </names>
    <locales>
      <locale><localeId>ko_KR.UTF-8</localeId><rank>1000</rank></locale>
    </locales>
    <languages>
      <language><languageId>ko</languageId><rank>1000</rank></language>
    </languages>
    <keyboards>
      <keyboard><keyboardId>kr</keyboardId><rank>1000</rank></keyboard>
    </keyboards>
    <timezones>
      <timezone><timezoneId>Asia/Seoul</timezoneId><rank>1000</rank></timezone>
    </timezones>
  </country>
  <country>
    <countryId>KW</countryId>
    <names>
      <name><languageId>de</languageId><name>Kuwait</name></name>
      <name><languageId>en</languageId><name>Kuwait</name></name>
    </names>
    <locales>
      <locale><localeId>ar_KW.UTF-8</localeId><rank>1000</rank></locale>
    </locales>
    <languages>
      <language><languageId>ar</languageId><rank>1000</rank></language>
    </languages>
    <keyboards>
      <keyboard><keyboardId>ara</keyboardId><rank>1000</rank></keyboard>
    </keyboards>
    <timezones>
      <timezone><timezoneId>Asia/Kuwait</timezoneId><rank>1000</rank></timezone>
    </timezones>
  </country>
  <country>
    <countryId>LB</countryId>
    <names>
      <name><languageId>de</languageId><name>Libanon</name></name>
      <name><languageId>en</languageId><name>Lebanon</name></name>
    </names>
    <locales>
      <locale><localeId>ar_LB.UTF-8</localeId><rank>1000</rank></locale>
    </locales>
    <languages>
      <language><languageId>ar</languageId><rank>1000</rank></language>
    </languages>
    <keyboards>
      <keyboard><keyboardId>ara</keyboardId><rank>1000</rank></keyboard>
    </keyboards>
    <timezones>
      <timezone><timezoneId>Asia/Beirut</timezoneId><rank>1000</rank></timezone>
    </timezones>
  </country>
  <country>
    <countryId>LK</countryId>
    <names>
      <name><languageId>de</languageId><name>Sri Lanka</name></name>
      <name><languageId>en</languageId><name>Sri Lanka</name></name>
      <name><languageId>si</languageId><name>ශ්‍රී ලංකාව</name></name>
    </names>
    <locales>
      <locale><localeId>si_LK.UTF-8</localeId><rank>1000</rank></locale>
    </locales>
    <languages>
      <language><languageId>si</languageId><rank>1000</rank></language>
    </languages>
    <keyboards>
      <keyboard><keyboardId>us</keyboardId><rank>1000</rank></keyboard>
    </keyboards>
    <timezones>
      <timezone><timezoneId>Asia/Colombo</timezoneId><rank>1000</rank></timezone>
    </timezones>
  </country>
  <country>
    <countryId>LY</countryId>
    <names>
      <name><languageId>de</languageId><name>Libyen</name></name>
      <name><languageId>en</languageId><name>Libya</name></name>
    </names>
    <locales>
      <locale><localeId>ar_LY.UTF-8</localeId><rank>1000</rank></locale>
    </locales>
    <languages>
      <language><languageId>ar</languageId><rank>1000</rank></language>
    </languages>
    <keyboards>
      <keyboard><keyboardId>ara</keyboardId><rank>1000</rank></keyboard>
    </keyboards>
    <timezones>
      <timezone><timezoneId>Africa/Tripoli</timezoneId><rank>1000</rank></timezone>
    </timezones>
  </country>
  <country>
    <countryId>MA</countryId>
    <names>
      <name><languageId>de</languageId><name>Marokko</name></name>
      <name><languageId>en</languageId><name>Morocco</name></name>
    </names>
    <locales>
      <locale><localeId>ar_MA.UTF-8</localeId><rank>1000</rank></locale>
    </locales>
    <languages>
      <language><languageId>ar</languageId><rank>1000</rank></language>
    </languages>
    <keyboards>
      <keyboard><keyboardId>ara</keyboardId><rank>1000</rank></keyboard>
    </keyboards>
    <timezones>
      <timezone><timezoneId>Africa/Casablanca</timezoneId><rank>1000</rank></timezone>
    </timezones>
  </country>
  <country>
    <countryId>ME</countryId>
    <names>
      <name><languageId>de</languageId><name>Montenegro</name></name>
      <name><languageId>en</languageId><name>Montenegro</name></name>
      <name><languageId>sr</languageId><name>Црна Гора</name></name>
      <name><languageId>sr_Latn</languageId><name>Crna Gora</name></name>
    </names>
    <locales>
      <locale><localeId>sr_ME.UTF-8</localeId><rank>1000</rank></locale>
    </locales>
    <languages>
      <language><languageId>sr</languageId><rank>1000</rank></language>
    </languages>
    <keyboards>
      <keyboard><keyboardId>sr</keyboardId><rank>1000</rank></keyboard>
    </keyboards>
    <timezones>
      <timezone><timezoneId>Europe/Podgorica</timezoneId><rank>1000</rank></timezone>
    </timezones>
  </country>
  <country>
    <countryId>MK</countryId>
    <names>
      <name><languageId>de</languageId><name>Mazedonien</name></name>
      <name><languageId>en</languageId><name>Macedonia</name></name>
      <name><languageId>mk</languageId><name>Македонија</name></name>
    </names>
    <locales>
      <locale><localeId>mk_MK.UTF-8</localeId><rank>900</rank></locale>
      <locale><localeId>sq_MK.UTF-8</localeId><rank>100</rank></locale>
    </locales>
    <languages>
      <language><languageId>mk</languageId><rank>900</rank></language>
      <language><languageId>sq</languageId><rank>100</rank></language>
    </languages>
    <keyboards>
      <keyboard><keyboardId>mk</keyboardId><rank>900</rank></keyboard>
      <keyboard><keyboardId>al</keyboardId><rank>100</rank></keyboard>
    </keyboards>
    <timezones>
      <timezone><timezoneId>Europe/Skopje</timezoneId><rank>1000</rank></timezone>
    </timezones>
  </country>
  <country>
    <countryId>MO</countryId>
    <names>
      <name><languageId>de</languageId><name>Sonderverwaltungszone Macao</name></name>
      <name><languageId>en</languageId><name>Macau SAR China</name></name>
      <name><languageId>zh</languageId><name>中国澳门特别行政区</name></name>
      <name><languageId>zh_Hant</languageId><name>中華人民共和國澳門特別行政區</name></name>
    </names>
    <locales>
      <locale><localeId>zh_HK.UTF-8</localeId><rank>1000</rank></locale>
      <locale><localeId>zh_MO.UTF-8</localeId><rank>0</rank></locale>
    </locales>
    <languages>
      <language><languageId>zh</languageId><rank>1000</rank></language>
    </languages>
    <keyboards>
      <keyboard><keyboardId>cn</keyboardId><rank>1000</rank></keyboard>
    </keyboards>
    <timezones>
      <timezone><timezoneId>Asia/Macau</timezoneId><rank>1000</rank></timezone>
    </timezones>
  </country>
  <country>
    <countryId>MY</countryId>
    <names>
      <name><languageId>de</languageId><name>Malaysia</name></name>
      <name><languageId>en</languageId><name>Malaysia</name></name>
      <name><languageId>ms</languageId><name>Malaysia</name></name>
    </names>
    <locales>
      <locale><localeId>ms_MY.UTF-8</localeId><rank>100</rank></locale>
    </locales>
    <languages>
      <language><languageId>ms</languageId><rank>1000</rank></language>
    </languages>
    <keyboards>
      <keyboard><keyboardId>us</keyboardId><rank>1000</rank></keyboard>
    </keyboards>
    <timezones>
      <timezone><timezoneId>Asia/Kuala_Lumpur</timezoneId><rank>800</rank></timezone>
      <timezone><timezoneId>Asia/Kuching</timezoneId><rank>200</rank></timezone>
    </timezones>
  </country>
  <country>
    <countryId>NL</countryId>
    <names>
      <name><languageId>de</languageId><name>Niederlande</name></name>
      <name><languageId>en</languageId><name>Netherlands</name></name>
      <name><languageId>nl</languageId><name>Nederland</name></name>
    </names>
    <locales>
      <locale><localeId>nl_NL.UTF-8</localeId><rank>950</rank></locale>
      <locale><localeId>fy_NL.UTF-8</localeId><rank>10</rank></locale>
      <locale><localeId>nds_NL.UTF-8</localeId><rank>9</rank></locale>
      <locale><localeId>li_NL.UTF-8</localeId><rank>8</rank></locale>
    </locales>
    <languages>
      <language><languageId>nl</languageId><rank>1000</rank></language>
      <language><languageId>fy</languageId><rank>10</rank></language>
      <language><languageId>nds</languageId><rank>9</rank></language>
      <language><languageId>li</languageId><rank>8</rank></language>
    </languages>
    <keyboards>
      <keyboard><keyboardId>us(euro)</keyboardId><rank>950</rank></keyboard>
      <keyboard><keyboardId>us(altgr-intl)</keyboardId><rank>50</rank></keyboard>
      <keyboard><keyboardId>nl</keyboardId><rank>0</rank></keyboard>
    </keyboards>
    <timezones>
      <timezone><timezoneId>Europe/Amsterdam</timezoneId><rank>1000</rank></timezone>
    </timezones>
  </country>
  <country>
    <countryId>NO</countryId>
    <names>
      <name><languageId>de</languageId><name>Norwegen</name></name>
      <name><languageId>en</languageId><name>Norway</name></name>
      <name><languageId>nb</languageId><name>Norge</name></name>
      <name><languageId>nn</languageId><name>Noreg</name></name>
    </names>
    <locales>
      <locale><localeId>nb_NO.UTF-8</localeId><rank>600</rank></locale>
      <locale><localeId>nn_NO.UTF-8</localeId><rank>300</rank></locale>
      <locale><localeId>se_NO.UTF-8</localeId><rank>100</rank></locale>
    </locales>
    <languages>
      <language><languageId>nn</languageId><rank>600</rank></language>
      <language><languageId>nb</languageId><rank>300</rank></language>
      <language><languageId>se</languageId><rank>100</rank></language>
    </languages>
    <keyboards>
      <keyboard><keyboardId>no</keyboardId><rank>1000</rank></keyboard>
    </keyboards>
    <timezones>
      <timezone><timezoneId>Europe/Oslo</timezoneId><rank>1000</rank></timezone>
    </timezones>
  </country>
  <country>
    <countryId>OM</countryId>
    <names>
      <name><languageId>de</languageId><name>Oman</name></name>
      <name><languageId>en</languageId><name>Oman</name></name>
    </names>
    <locales>
      <locale><localeId>ar_OM.UTF-8</localeId><rank>1000</rank></locale>
    </locales>
    <languages>
      <language><languageId>ar</languageId><rank>1000</rank></language>
    </languages>
    <keyboards>
      <keyboard><keyboardId>ara</keyboardId><rank>1000</rank></keyboard>
    </keyboards>
    <timezones>
      <timezone><timezoneId>Asia/Muscat</timezoneId><rank>1000</rank></timezone>
    </timezones>
  </country>
  <country>
    <countryId>PK</countryId>
    <names>
      <name><languageId>de</languageId><name>Pakistan</name></name>
      <name><languageId>en</languageId><name>Pakistan</name></name>
      <name><languageId>ur</languageId><name>پاکستان</name></name>
    </names>
    <locales>
      <locale><localeId>ur_PK.UTF-8</localeId><rank>600</rank></locale>
      <locale><localeId>pa_PK.UTF-8</localeId><rank>400</rank></locale>
    </locales>
    <languages>
      <language><languageId>ur</languageId><rank>600</rank></language>
      <language><languageId>pa</languageId><rank>400</rank></language>
    </languages>
    <keyboards>
      <keyboard><keyboardId>us</keyboardId><rank>1000</rank></keyboard>
    </keyboards>
    <timezones>
      <timezone><timezoneId>Asia/Karachi</timezoneId><rank>1000</rank></timezone>
    </timezones>
  </country>
  <country>
    <countryId>PL</countryId>
    <names>
      <name><languageId>de</languageId><name>Polen</name></name>
      <name><languageId>en</languageId><name>Poland</name></name>
      <name><languageId>pl</languageId><name>Polska</name></name>
    </names>
    <locales>
      <locale><localeId>pl_PL.UTF-8</localeId><rank>990</rank></locale>
      <locale><localeId>csb_PL.UTF-8</localeId><rank>10</rank></locale>
    </locales>
    <languages>
      <language><languageId>pl</languageId><rank>990</rank></language>
      <language><languageId>csb</languageId><rank>10</rank></language>
    </languages>
    <keyboards>
      <keyboard><keyboardId>pl</keyboardId><rank>1000</rank></keyboard>
    </keyboards>
    <timezones>
      <timezone><timezoneId>Europe/Warsaw</timezoneId><rank>1000</rank></timezone>
    </timezones>
  </country>
  <country>
    <countryId>QA</countryId>
    <names>
      <name><languageId>de</languageId><name>Katar</name></name>
      <name><languageId>en</languageId><name>Qatar</name></name>
    </names>
    <locales>
      <locale><localeId>ar_QA.UTF-8</localeId><rank>1000</rank></locale>
    </locales>
    <languages>
      <language><languageId>ar</languageId><rank>1000</rank></language>
    </languages>
    <keyboards>
      <keyboard><keyboardId>ara</keyboardId><rank>1000</rank></keyboard>
    </keyboards>
    <timezones>
      <timezone><timezoneId>Asia/Qatar</timezoneId><rank>1000</rank></timezone>
    </timezones>
  </country>
  <country>
    <countryId>RS</countryId>
    <names>
      <name><languageId>de</languageId><name>Serbien</name></name>
      <name><languageId>en</languageId><name>Serbia</name></name>
      <name><languageId>sr</languageId><name>Србија</name></name>
      <name><languageId>sr_Latn</languageId><name>Srbija</name></name>
    </names>
    <locales>
      <locale><localeId>sr_RS.UTF-8</localeId><rank>600</rank></locale>
      <locale><localeId>sr_RS.UTF-8@latin</localeId><rank>400</rank></locale>
    </locales>
    <languages>
      <language><languageId>sr</languageId><rank>1000</rank></language>
    </languages>
    <keyboards>
      <keyboard><keyboardId>sr</keyboardId><rank>600</rank></keyboard>
      <keyboard><keyboardId>sr(latin)</keyboardId><rank>400</rank></keyboard>
    </keyboards>
    <timezones>
      <timezone><timezoneId>Europe/Belgrade</timezoneId><rank>1000</rank></timezone>
    </timezones>
  </country>
  <country>
    <countryId>RU</countryId>
    <names>
      <name><languageId>de</languageId><name>Russland</name></name>
      <name><languageId>en</languageId><name>Russia</name></name>
    </names>
    <locales>
      <locale><localeId>ru_RU.UTF-8</localeId><rank>950</rank></locale>
      <locale><localeId>cv_RU.UTF-8</localeId><rank>12</rank></locale>
      <locale><localeId>mhr_RU.UTF-8</localeId><rank>11</rank></locale>
      <locale><localeId>os_RU.UTF-8</localeId><rank>10</rank></locale>
      <locale><localeId>tt_RU.UTF-8</localeId><rank>9</rank></locale>
    </locales>
    <languages>
      <language><languageId>ru</languageId><rank>950</rank></language>
      <language><languageId>cv</languageId><rank>12</rank></language>
      <language><languageId>mhr</languageId><rank>11</rank></language>
      <language><languageId>os</languageId><rank>10</rank></language>
      <language><languageId>tt</languageId><rank>9</rank></language>
    </languages>
    <keyboards>
      <keyboard><keyboardId>ru</keyboardId><rank>1000</rank></keyboard>
    </keyboards>
    <timezones>
      <timezone><timezoneId>Europe/Moscow</timezoneId><rank>300</rank></timezone>
      <timezone><timezoneId>Europe/Kaliningrad</timezoneId><rank>50</rank></timezone>
      <timezone><timezoneId>Europe/Volgograd</timezoneId><rank>49</rank></timezone>
      <timezone><timezoneId>Europe/Samara</timezoneId><rank>48</rank></timezone>
      <timezone><timezoneId>Asia/Yekaterinburg</timezoneId><rank>47</rank></timezone>
      <timezone><timezoneId>Asia/Omsk</timezoneId><rank>46</rank></timezone>
      <timezone><timezoneId>Asia/Novosibirsk</timezoneId><rank>45</rank></timezone>
      <timezone><timezoneId>Asia/Novokuznetsk</timezoneId><rank>44</rank></timezone>
      <timezone><timezoneId>Asia/Krasnoyarsk</timezoneId><rank>43</rank></timezone>
      <timezone><timezoneId>Asia/Irkutsk</timezoneId><rank>42</rank></timezone>
      <timezone><timezoneId>Asia/Yakutsk</timezoneId><rank>41</rank></timezone>
      <timezone><timezoneId>Asia/Khandyga</timezoneId><rank>40</rank></timezone>
      <timezone><timezoneId>Asia/Vladivostok</timezoneId><rank>39</rank></timezone>
      <timezone><timezoneId>Asia/Sakhalin</timezoneId><rank>38</rank></timezone>
      <timezone><timezoneId>Asia/Ust-Nera</timezoneId><rank>37</rank></timezone>
      <timezone><timezoneId>Asia/Magadan</timezoneId><rank>36</rank></timezone>
      <timezone><timezoneId>Asia/Kamchatka</timezoneId><rank>35</rank></timezone>
      <timezone><timezoneId>Asia/Anadyr</timezoneId><rank>34</rank></timezone>
    </timezones>
  </country>
  <country>
    <countryId>SA</countryId>
    <names>
      <name><languageId>de</languageId><name>Saudi-Arabien</name></name>
      <name><languageId>en</languageId><name>Saudi Arabia</name></name>
    </names>
    <locales>
      <locale><localeId>ar_SA.UTF-8</localeId><rank>1000</rank></locale>
    </locales>
    <languages>
      <language><languageId>ar</languageId><rank>1000</rank></language>
    </languages>
    <keyboards>
      <keyboard><keyboardId>ara</keyboardId><rank>1000</rank></keyboard>
    </keyboards>
    <timezones>
      <timezone><timezoneId>Asia/Riyadh</timezoneId><rank>1000</rank></timezone>
    </timezones>
  </country>
  <country>
    <countryId>SD</countryId>
    <names>
      <name><languageId>de</languageId><name>Sudan</name></name>
      <name><languageId>en</languageId><name>Sudan</name></name>
    </names>
    <locales>
      <locale><localeId>ar_SD.UTF-8</localeId><rank>1000</rank></locale>
    </locales>
    <languages>
      <language><languageId>ar</languageId><rank>1000</rank></language>
    </languages>
    <keyboards>
      <keyboard><keyboardId>ara</keyboardId><rank>1000</rank></keyboard>
    </keyboards>
    <timezones>
      <timezone><timezoneId>Africa/Khartoum</timezoneId><rank>1000</rank></timezone>
    </timezones>
  </country>
  <country>
    <countryId>SE</countryId>
    <names>
    </names>
    <locales>
      <locale><localeId>sv_SE.UTF-8</localeId><rank>1000</rank></locale>
    </locales>
    <languages>
      <language><languageId>sv</languageId><rank>1000</rank></language>
    </languages>
    <keyboards>
      <keyboard><keyboardId>se</keyboardId><rank>1000</rank></keyboard>
    </keyboards>
    <timezones>
      <timezone><timezoneId>Europe/Stockholm</timezoneId><rank>1000</rank></timezone>
    </timezones>
  </country>
  <country>
    <countryId>SG</countryId>
    <names>
      <name><languageId>de</languageId><name>Singapur</name></name>
      <name><languageId>en</languageId><name>Singapore</name></name>
      <name><languageId>zh</languageId><name>新加坡</name></name>
      <name><languageId>zh_Hant</languageId><name>新加坡</name></name>
    </names>
    <locales>
      <locale><localeId>zh_SG.UTF-8</localeId><rank>1000</rank></locale>
      <locale><localeId>en_SG.UTF-8</localeId><rank>1000</rank></locale>
    </locales>
    <languages>
      <language><languageId>en</languageId><rank>1000</rank></language>
      <language><languageId>zh</languageId><rank>1000</rank></language>
    </languages>
    <keyboards>
      <keyboard><keyboardId>us</keyboardId><rank>600</rank></keyboard>
      <keyboard><keyboardId>cn</keyboardId><rank>400</rank></keyboard>
    </keyboards>
    <timezones>
      <timezone><timezoneId>Asia/Singapore</timezoneId><rank>1000</rank></timezone>
    </timezones>
  </country>
  <country>
    <countryId>SK</countryId>
    <names>
      <name><languageId>de</languageId><name>Slowakei</name></name>
      <name><languageId>en</languageId><name>Slovakia</name></name>
      <name><languageId>sk</languageId><name>Slovenská republika</name></name>
    </names>
    <locales>
      <locale><localeId>sk_SK.UTF-8</localeId><rank>1000</rank></locale>
    </locales>
    <languages>
      <language><languageId>sk</languageId><rank>1000</rank></language>
    </languages>
    <keyboards>
      <keyboard><keyboardId>sk</keyboardId><rank>1000</rank></keyboard>
    </keyboards>
    <timezones>
      <timezone><timezoneId>Europe/Bratislava</timezoneId><rank>1000</rank></timezone>
    </timezones>
  </country>
  <country>
    <countryId>SY</countryId>
    <names>
      <name><languageId>de</languageId><name>Syrien</name></name>
      <name><languageId>en</languageId><name>Syria</name></name>
    </names>
    <locales>
      <locale><localeId>ar_SY.UTF-8</localeId><rank>1000</rank></locale>
    </locales>
    <languages>
      <language><languageId>ar</languageId><rank>1000</rank></language>
    </languages>
    <keyboards>
      <keyboard><keyboardId>ara</keyboardId><rank>1000</rank></keyboard>
    </keyboards>
    <timezones>
      <timezone><timezoneId>Asia/Damascus</timezoneId><rank>1000</rank></timezone>
    </timezones>
  </country>
  <country>
    <countryId>TN</countryId>
    <names>
      <name><languageId>de</languageId><name>Tunesien</name></name>
      <name><languageId>en</languageId><name>Tunisia</name></name>
    </names>
    <locales>
      <locale><localeId>ar_TN.UTF-8</localeId><rank>1000</rank></locale>
    </locales>
    <languages>
      <language><languageId>ar</languageId><rank>1000</rank></language>
    </languages>
    <keyboards>
      <keyboard><keyboardId>ara</keyboardId><rank>1000</rank></keyboard>
    </keyboards>
    <timezones>
      <timezone><timezoneId>Africa/Tunis</timezoneId><rank>1000</rank></timezone>
    </timezones>
  </country>
  <country>
    <countryId>TR</countryId>
    <names>
      <name><languageId>de</languageId><name>Türkei</name></name>
      <name><languageId>en</languageId><name>Turkey</name></name>
      <name><languageId>tr</languageId><name>Türkiye</name></name>
    </names>
    <locales>
      <locale><localeId>tr_TR.UTF-8</localeId><rank>900</rank></locale>
      <locale><localeId>ku_TR.UTF-8</localeId><rank>100</rank></locale>
    </locales>
    <languages>
      <language><languageId>tr</languageId><rank>900</rank></language>
      <language><languageId>ku</languageId><rank>100</rank></language>
    </languages>
    <keyboards>
      <keyboard><keyboardId>tr</keyboardId><rank>1000</rank></keyboard>
    </keyboards>
    <timezones>
      <timezone><timezoneId>Europe/Istanbul</timezoneId><rank>1000</rank></timezone>
    </timezones>
  </country>
  <country>
    <countryId>TW</countryId>
    <names>
      <name><languageId>de</languageId><name>Taiwan</name></name>
      <name><languageId>en</languageId><name>Taiwan</name></name>
      <name><languageId>zh</languageId><name>台湾</name></name>
      <name><languageId>zh_CN</languageId><name>中华民国</name></name>
      <name><languageId>zh_Hant</languageId><name>台灣</name></name>
      <name><languageId>zh_TW</languageId><name>台灣</name></name>
    </names>
    <locales>
      <locale><localeId>zh_TW.UTF-8</localeId><rank>1000</rank></locale>
    </locales>
    <languages>
      <language><languageId>zh</languageId><rank>1000</rank></language>
    </languages>
    <keyboards>
      <keyboard><keyboardId>cn</keyboardId><rank>1000</rank></keyboard>
    </keyboards>
    <timezones>
      <timezone><timezoneId>Asia/Taipei</timezoneId><rank>1000</rank></timezone>
    </timezones>
  </country>
  <country>
    <countryId>UA</countryId>
    <names>
      <name><languageId>de</languageId><name>Ukraine</name></name>
      <name><languageId>en</languageId><name>Ukraine</name></name>
      <name><languageId>uk</languageId><name>Україна</name></name>
    </names>
    <locales>
      <locale><localeId>uk_UA.UTF-8</localeId><rank>900</rank></locale>
      <locale><localeId>ru_UA.UTF-8</localeId><rank>100</rank></locale>
    </locales>
    <languages>
      <language><languageId>uk</languageId><rank>900</rank></language>
      <language><languageId>ru</languageId><rank>100</rank></language>
    </languages>
    <keyboards>
      <keyboard><keyboardId>ua</keyboardId><rank>900</rank></keyboard>
      <keyboard><keyboardId>ru</keyboardId><rank>100</rank></keyboard>
    </keyboards>
    <timezones>
    </timezones>
  </country>
  <country>
    <countryId>VN</countryId>
    <names>
      <name><languageId>de</languageId><name>Việt Nam</name></name>
      <name><languageId>en</languageId><name>Vietnam</name></name>
      <name><languageId>vi</languageId><name>Vietnam</name></name>
    </names>
    <locales>
      <locale><localeId>vi_VN.UTF-8</localeId><rank>1000</rank></locale>
    </locales>
    <languages>
      <language><languageId>vi</languageId><rank>1000</rank></language>
    </languages>
    <keyboards>
      <keyboard><keyboardId>vn</keyboardId><rank>1000</rank></keyboard>
    </keyboards>
    <timezones>
      <timezone><timezoneId>Asia/Ho_Chi_Minh</timezoneId><rank>1000</rank></timezone>
    </timezones>
  </country>
  <country>
    <countryId>YE</countryId>
    <names>
      <name><languageId>de</languageId><name>Jemen</name></name>
      <name><languageId>en</languageId><name>Yemen</name></name>
    </names>
    <locales>
      <locale><localeId>ar_YE.UTF-8</localeId><rank>1000</rank></locale>
    </locales>
    <languages>
      <language><languageId>ar</languageId><rank>1000</rank></language>
    </languages>
    <keyboards>
      <keyboard><keyboardId>ara</keyboardId><rank>1000</rank></keyboard>
    </keyboards>
    <timezones>
      <timezone><timezoneId>Asia/Aden</timezoneId><rank>1000</rank></timezone>
    </timezones>
  </country>
  <country>
    <countryId>ZA</countryId>
    <names>
      <name><languageId>de</languageId><name>Südafrica</name></name>
      <name><languageId>en</languageId><name>South Africa</name></name>
    </names>
    <locales>
      <locale><localeId>zu_ZA.UTF-8</localeId><rank>227</rank></locale>
      <locale><localeId>xh_ZA.UTF-8</localeId><rank>160</rank></locale>
      <locale><localeId>af_ZA.UTF-8</localeId><rank>135</rank></locale>
      <locale><localeId>en_ZA.UTF-8</localeId><rank>96</rank></locale>
      <locale><localeId>nso_ZA.UTF-8</localeId><rank>91</rank></locale>
      <locale><localeId>tn_ZA.UTF-8</localeId><rank>80</rank></locale>
      <locale><localeId>st_ZA.UTF-8</localeId><rank>76</rank></locale>
      <locale><localeId>ts_ZA.UTF-8</localeId><rank>45</rank></locale>
      <locale><localeId>ss_ZA.UTF-8</localeId><rank>25</rank></locale>
      <locale><localeId>ve_ZA.UTF-8</localeId><rank>24</rank></locale>
      <locale><localeId>nr_ZA.UTF-8</localeId><rank>21</rank></locale>
    </locales>
    <languages>
      <language><languageId>zu</languageId><rank>227</rank></language>
      <language><languageId>xh</languageId><rank>160</rank></language>
      <language><languageId>af</languageId><rank>135</rank></language>
      <language><languageId>en</languageId><rank>96</rank></language>
      <language><languageId>nso</languageId><rank>91</rank></language>
      <language><languageId>tn</languageId><rank>80</rank></language>
      <language><languageId>st</languageId><rank>76</rank></language>
      <language><languageId>ts</languageId><rank>45</rank></language>
      <language><languageId>ss</languageId><rank>25</rank></language>
      <language><languageId>ve</languageId><rank>24</rank></language>
      <language><languageId>nr</languageId><rank>21</rank></language>
    </languages>
    <keyboards>
      <keyboard><keyboardId>us</keyboardId><rank>1000</rank></keyboard>
    </keyboards>
    <timezones>
      <timezone><timezoneId>Africa/Johannesburg</timezoneId><rank>1000</rank></timezone>
    </timezones>
  </country>
</countries>
