<?xml version="1.0" encoding="UTF-8"?>
<languages>
  <language>
    <languageId>af</languageId>
    <iso639-1>af</iso639-1>
    <iso639-2-t>afr</iso639-2-t>
    <iso639-2-b>afr</iso639-2-b>
    <names>
      <name><languageId>af</languageId><name>Afrikaans</name></name>
      <name><languageId>de</languageId><name>Afrikaans</name></name>
      <name><languageId>en</languageId><name>Afrikaans</name></name>
    </names>
    <locales>
      <locale><localeId>af_ZA.UTF-8</localeId><rank>1000</rank></locale>
    </locales>
    <countries>
      <country><countryId>ZA</countryId><rank>1000</rank></country>
    </countries>
    <keyboards>
      <keyboard><keyboardId>us</keyboardId><rank>1000</rank></keyboard>
    </keyboards>
    <timezones>
      <timezone><timezoneId>Africa/Johannesburg</timezoneId><rank>1000</rank></timezone>
    </timezones>
  </language>
  <language>
    <languageId>ar</languageId>
    <iso639-1>ara</iso639-1>
    <iso639-2-t>ara</iso639-2-t>
    <iso639-2-b>ara</iso639-2-b>
    <names>
      <name><languageId>ar</languageId><name>العربية</name></name>
      <name><languageId>de</languageId><name>Arabisch</name></name>
      <name><languageId>en</languageId><name>Arabic</name></name>
    </names>
    <locales>
      <locale><localeId>ar_EG.UTF-8</localeId><rank>300</rank></locale>
      <locale><localeId>ar_SD.UTF-8</localeId><rank>170</rank></locale>
      <locale><localeId>ar_DZ.UTF-8</localeId><rank>150</rank></locale>
      <locale><localeId>ar_MA.UTF-8</localeId><rank>140</rank></locale>
      <locale><localeId>ar_IQ.UTF-8</localeId><rank>130</rank></locale>
      <locale><localeId>ar_SA.UTF-8</localeId><rank>120</rank></locale>
      <locale><localeId>ar_YE.UTF-8</localeId><rank>110</rank></locale>
      <locale><localeId>ar_SY.UTF-8</localeId><rank>100</rank></locale>
      <locale><localeId>ar_TN.UTF-8</localeId><rank>50</rank></locale>
      <locale><localeId>ar_LY.UTF-8</localeId><rank>45</rank></locale>
      <locale><localeId>ar_JO.UTF-8</localeId><rank>40</rank></locale>
      <locale><localeId>ar_AE.UTF-8</localeId><rank>35</rank></locale>
      <locale><localeId>ar_LB.UTF-8</localeId><rank>30</rank></locale>
      <locale><localeId>ar_KW.UTF-8</localeId><rank>25</rank></locale>
      <locale><localeId>ar_OM.UTF-8</localeId><rank>15</rank></locale>
      <locale><localeId>ar_QA.UTF-8</localeId><rank>10</rank></locale>
      <locale><localeId>ar_BH.UTF-8</localeId><rank>9</rank></locale>
      <locale><localeId>ar_IN.UTF-8</localeId><rank>1</rank></locale>
    </locales>
    <countries>
      <country><countryId>EG</countryId><rank>300</rank></country>
      <country><countryId>SD</countryId><rank>170</rank></country>
      <country><countryId>DZ</countryId><rank>150</rank></country>
      <country><countryId>MA</countryId><rank>140</rank></country>
      <country><countryId>IQ</countryId><rank>130</rank></country>
      <country><countryId>SA</countryId><rank>120</rank></country>
      <country><countryId>YE</countryId><rank>110</rank></country>
      <country><countryId>SY</countryId><rank>100</rank></country>
      <country><countryId>TN</countryId><rank>50</rank></country>
      <country><countryId>LY</countryId><rank>45</rank></country>
      <country><countryId>JO</countryId><rank>40</rank></country>
      <country><countryId>AE</countryId><rank>35</rank></country>
      <country><countryId>LB</countryId><rank>30</rank></country>
      <country><countryId>KW</countryId><rank>25</rank></country>
      <country><countryId>OM</countryId><rank>15</rank></country>
      <country><countryId>QA</countryId><rank>10</rank></country>
      <country><countryId>BH</countryId><rank>9</rank></country>
      <country><countryId>IN</countryId><rank>1</rank></country>
    </countries>
    <keyboards>
      <keyboard><keyboardId>ara</keyboardId><rank>700</rank></keyboard>
      <keyboard><keyboardId>ara(azerty)</keyboardId><rank>100</rank></keyboard>
      <keyboard><keyboardId>iq</keyboardId><rank>10</rank></keyboard>
      <keyboard><keyboardId>ma</keyboardId><rank>9</rank></keyboard>
      <keyboard><keyboardId>sy</keyboardId><rank>8</rank></keyboard>
    </keyboards>
    <timezones>
      <timezone><timezoneId>Africa/Cairo</timezoneId><rank>300</rank></timezone>
      <timezone><timezoneId>Africa/Khartoum</timezoneId><rank>170</rank></timezone>
      <timezone><timezoneId>Africa/Algiers</timezoneId><rank>150</rank></timezone>
      <timezone><timezoneId>Africa/Casablanca</timezoneId><rank>140</rank></timezone>
      <timezone><timezoneId>Asia/Baghdad</timezoneId><rank>130</rank></timezone>
      <timezone><timezoneId>Asia/Riyadh</timezoneId><rank>120</rank></timezone>
      <timezone><timezoneId>Asia/Aden</timezoneId><rank>110</rank></timezone>
      <timezone><timezoneId>Asia/Damascus</timezoneId><rank>100</rank></timezone>
      <timezone><timezoneId>Africa/Tunis</timezoneId><rank>50</rank></timezone>
      <timezone><timezoneId>Africa/Tripoli</timezoneId><rank>45</rank></timezone>
      <timezone><timezoneId>Asia/Amman</timezoneId><rank>40</rank></timezone>
      <timezone><timezoneId>Asia/Dubai</timezoneId><rank>35</rank></timezone>
      <timezone><timezoneId>Asia/Beirut</timezoneId><rank>30</rank></timezone>
      <timezone><timezoneId>Asia/Kuwait</timezoneId><rank>25</rank></timezone>
      <timezone><timezoneId>Asia/Muscat</timezoneId><rank>15</rank></timezone>
      <timezone><timezoneId>Asia/Qatar</timezoneId><rank>10</rank></timezone>
      <timezone><timezoneId>Asia/Bahrain</timezoneId><rank>9</rank></timezone>
      <timezone><timezoneId>Asia/Kolkata</timezoneId><rank>1</rank></timezone>
    </timezones>
  </language>
  <language>
    <languageId>as</languageId>
    <iso639-1>as</iso639-1>
    <iso639-2-t>asm</iso639-2-t>
    <iso639-2-b>asm</iso639-2-b>
    <names>
      <name><languageId>as</languageId><name>অসমীয়া</name></name>
      <name><languageId>de</languageId><name>Assamesisch</name></name>
      <name><languageId>en</languageId><name>Assamese</name></name>
    </names>
    <locales>
      <locale><localeId>as_IN.UTF-8</localeId><rank>1000</rank></locale>
    </locales>
    <countries>
      <country><countryId>IN</countryId><rank>990</rank></country>
      <country><countryId>BD</countryId><rank>2</rank></country>
      <country><countryId>BT</countryId><rank>1</rank></country>
    </countries>
    <keyboards>
      <keyboard><keyboardId>us</keyboardId><rank>1000</rank></keyboard>
    </keyboards>
    <timezones>
      <timezone><timezoneId>Asia/Kolkata</timezoneId><rank>1000</rank></timezone>
    </timezones>
  </language>
  <language>
    <languageId>be</languageId>
    <iso639-1>be</iso639-1>
    <iso639-2-t>bel</iso639-2-t>
    <iso639-2-b>bel</iso639-2-b>
    <names>
      <name><languageId>be</languageId><name>беларуская</name></name>
      <name><languageId>de</languageId><name>Weißrussich</name></name>
      <name><languageId>de_CH</languageId><name>Weissrussich</name></name>
      <name><languageId>en</languageId><name>Belarusian</name></name>
    </names>
    <locales>
      <locale><localeId>be_BY.UTF-8</localeId><rank>980</rank></locale>
      <locale><localeId>be_BY.UTF-8@latin</localeId><rank>20</rank></locale>
    </locales>
    <countries>
      <country><countryId>BY</countryId><rank>1000</rank></country>
    </countries>
    <keyboards>
      <keyboard><keyboardId>by</keyboardId><rank>950</rank></keyboard>
      <keyboard><keyboardId>by(latin)</keyboardId><rank>0</rank></keyboard>
      <keyboard><keyboardId>by(legacy)</keyboardId><rank>0</rank></keyboard>
    </keyboards>
    <timezones>
      <timezone><timezoneId>Europe/Minsk</timezoneId><rank>1000</rank></timezone>
    </timezones>
  </language>
  <language>
    <languageId>bg</languageId>
    <iso639-1>bg</iso639-1>
    <iso639-2-t>bul</iso639-2-t>
    <iso639-2-b>bul</iso639-2-b>
    <names>
      <name><languageId>bg</languageId><name>български</name></name>
      <name><languageId>de</languageId><name>Bulgarisch</name></name>
      <name><languageId>en</languageId><name>Bulgarian</name></name>
    </names>
    <locales>
      <locale><localeId>bg_BG.UTF-8</localeId><rank>1000</rank></locale>
    </locales>
    <countries>
      <country><countryId>BG</countryId><rank>1000</rank></country>
    </countries>
    <keyboards>
      <keyboard><keyboardId>bg</keyboardId><rank>1000</rank></keyboard>
    </keyboards>
    <timezones>
      <timezone><timezoneId>Europe/Sofia</timezoneId><rank>1000</rank></timezone>
    </timezones>
  </language>
  <language>
    <languageId>bn</languageId>
    <iso639-1>bn</iso639-1>
    <iso639-2-t>ben</iso639-2-t>
    <iso639-2-b>ben</iso639-2-b>
    <names>
      <name><languageId>bn</languageId><name>বাংলা</name></name>
      <name><languageId>de</languageId><name>Bengalisch</name></name>
      <name><languageId>en</languageId><name>Bengali</name></name>
    </names>
    <locales>
      <locale><localeId>bn_BD.UTF-8</localeId><rank>700</rank></locale>
      <locale><localeId>bn_IN.UTF-8</localeId><rank>300</rank></locale>
    </locales>
    <countries>
      <country><countryId>BD</countryId><rank>700</rank></country>
      <country><countryId>IN</countryId><rank>300</rank></country>
    </countries>
    <keyboards>
      <keyboard><keyboardId>us</keyboardId><rank>950</rank></keyboard>
    </keyboards>
    <timezones>
      <timezone><timezoneId>Asia/Dhaka</timezoneId><rank>700</rank></timezone>
      <timezone><timezoneId>Asia/Kolkata</timezoneId><rank>300</rank></timezone>
    </timezones>
  </language>
  <language>
    <languageId>ca</languageId>
    <iso639-1>ca</iso639-1>
    <iso639-2-t>cat</iso639-2-t>
    <iso639-2-b>cat</iso639-2-b>
    <names>
      <name><languageId>ca</languageId><name>català</name></name>
      <name><languageId>de</languageId><name>Katalanisch</name></name>
      <name><languageId>en</languageId><name>Catalan</name></name>
    </names>
    <locales>
      <locale><localeId>ca_ES.UTF-8</localeId><rank>900</rank></locale>
      <locale><localeId>ca_FR.UTF-8</localeId><rank>100</rank></locale>
      <locale><localeId>ca_AD.UTF-8</localeId><rank>50</rank></locale>
      <locale><localeId>ca_IT.UTF-8</localeId><rank>10</rank></locale>
    </locales>
    <countries>
      <country><countryId>ES</countryId><rank>900</rank></country>
      <country><countryId>FR</countryId><rank>100</rank></country>
      <country><countryId>AD</countryId><rank>50</rank></country>
      <country><countryId>IT</countryId><rank>10</rank></country>
    </countries>
    <keyboards>
      <keyboard><keyboardId>es(cat)</keyboardId><rank>1000</rank></keyboard>
      <keyboard><keyboardId>ad</keyboardId><rank>0</rank></keyboard>
    </keyboards>
    <timezones>
      <timezone><timezoneId>Europe/Madrid</timezoneId><rank>900</rank></timezone>
      <timezone><timezoneId>Europe/Paris</timezoneId><rank>100</rank></timezone>
      <timezone><timezoneId>Europe/Andorra</timezoneId><rank>50</rank></timezone>
      <timezone><timezoneId>Europe/Rome</timezoneId><rank>10</rank></timezone>
    </timezones>
  </language>
  <language>
    <languageId>cs</languageId>
    <iso639-1>cs</iso639-1>
    <iso639-2-t>ces</iso639-2-t>
    <iso639-2-b>cze</iso639-2-b>
    <names>
      <name><languageId>cs</languageId><name>čeština</name></name>
      <name><languageId>de</languageId><name>Tschechisch</name></name>
      <name><languageId>en</languageId><name>Czech</name></name>
    </names>
    <locales>
      <locale><localeId>cs_CZ.UTF-8</localeId><rank>900</rank></locale>
    </locales>
    <countries>
      <country><countryId>CZ</countryId><rank>900</rank></country>
    </countries>
    <keyboards>
      <keyboard><keyboardId>cz</keyboardId><rank>1000</rank></keyboard>
    </keyboards>
    <timezones>
      <timezone><timezoneId>Europe/Prague</timezoneId><rank>1000</rank></timezone>
    </timezones>
  </language>
  <language>
    <languageId>csb</languageId>
    <iso639-1>None</iso639-1>
    <iso639-2-t>csb</iso639-2-t>
    <iso639-2-b>csb</iso639-2-b>
    <names>
      <name><languageId>de</languageId><name>Kaschubisch</name></name>
      <name><languageId>en</languageId><name>Kashubian</name></name>
      <name><languageId>pl</languageId><name>kaszubski</name></name>
    </names>
    <locales>
      <locale><localeId>csb_PL.UTF-8</localeId><rank>1000</rank></locale>
    </locales>
    <countries>
      <country><countryId>PL</countryId><rank>1000</rank></country>
    </countries>
    <keyboards>
      <keyboard><keyboardId>pl</keyboardId><rank>1000</rank></keyboard>
    </keyboards>
    <timezones>
      <timezone><timezoneId>Europe/Warsaw</timezoneId><rank>1000</rank></timezone>
    </timezones>
  </language>
  <language>
    <languageId>cy</languageId>
    <iso639-1>cy</iso639-1>
    <iso639-2-t>cym</iso639-2-t>
    <iso639-2-b>wel</iso639-2-b>
    <names>
      <name><languageId>cy</languageId><name>Cymraeg</name></name>
      <name><languageId>de</languageId><name>Walisisch</name></name>
      <name><languageId>en</languageId><name>Welsh</name></name>
    </names>
    <locales>
      <locale><localeId>cy_GB.UTF-8</localeId><rank>1000</rank></locale>
    </locales>
    <countries>
      <country><countryId>GB</countryId><rank>1000</rank></country>
    </countries>
    <keyboards>
      <keyboard><keyboardId>gb</keyboardId><rank>1000</rank></keyboard>
    </keyboards>
    <timezones>
      <timezone><timezoneId>Europe/London</timezoneId><rank>1000</rank></timezone>
    </timezones>
  </language>
  <language>
    <languageId>da</languageId>
    <iso639-1>da</iso639-1>
    <iso639-2-t>dan</iso639-2-t>
    <iso639-2-b>dan</iso639-2-b>
    <names>
      <name><languageId>da</languageId><name>dansk</name></name>
      <name><languageId>de</languageId><name>Dänisch</name></name>
      <name><languageId>en</languageId><name>Danish</name></name>
    </names>
    <locales>
      <locale><localeId>da_DK.UTF-8</localeId><rank>950</rank></locale>
      <locale><localeId>en_DK.UTF-8</localeId><rank>50</rank></locale>
    </locales>
    <countries>
      <country><countryId>DK</countryId><rank>1000</rank></country>
    </countries>
    <keyboards>
      <keyboard><keyboardId>dk</keyboardId><rank>1000</rank></keyboard>
    </keyboards>
    <timezones>
      <timezone><timezoneId>Europe/Copenhagen</timezoneId><rank>1000</rank></timezone>
    </timezones>
  </language>
  <language>
    <languageId>de</languageId>
    <iso639-1>de</iso639-1>
    <iso639-2-t>deu</iso639-2-t>
    <iso639-2-b>ger</iso639-2-b>
    <names>
      <name><languageId>de</languageId><name>Deutsch</name></name>
      <name><languageId>en</languageId><name>German</name></name>
    </names>
    <locales>
      <locale><localeId>de_DE.UTF-8</localeId><rank>600</rank></locale>
      <locale><localeId>de_AT.UTF-8</localeId><rank>200</rank></locale>
      <locale><localeId>de_CH.UTF-8</localeId><rank>90</rank></locale>
      <locale><localeId>de_BE.UTF-8</localeId><rank>10</rank></locale>
    </locales>
    <countries>
      <country><countryId>DE</countryId><rank>600</rank></country>
      <country><countryId>AT</countryId><rank>200</rank></country>
      <country><countryId>CH</countryId><rank>90</rank></country>
      <country><countryId>BE</countryId><rank>10</rank></country>
    </countries>
    <keyboards>
      <keyboard><keyboardId>de(nodeadkeys)</keyboardId><rank>700</rank></keyboard>
      <keyboard><keyboardId>de(deadacute)</keyboardId><rank>100</rank></keyboard>
      <keyboard><keyboardId>at(nodeadkeys)</keyboardId><rank>50</rank></keyboard>
      <keyboard><keyboardId>ch</keyboardId><rank>49</rank></keyboard>
      <keyboard><keyboardId>be(oss)</keyboardId><rank>1</rank></keyboard>
    </keyboards>
    <timezones>
      <timezone><timezoneId>Europe/Berlin</timezoneId><rank>700</rank></timezone>
      <timezone><timezoneId>Europe/Vienna</timezoneId><rank>200</rank></timezone>
      <timezone><timezoneId>Europe/Zurich</timezoneId><rank>100</rank></timezone>
    </timezones>
  </language>
  <language>
    <languageId>el</languageId>
    <iso639-1>el</iso639-1>
    <iso639-2-t>ell</iso639-2-t>
    <iso639-2-b>gre</iso639-2-b>
    <names>
      <name><languageId>de</languageId><name>Griechisch</name></name>
      <name><languageId>el</languageId><name>Ελληνικά</name></name>
      <name><languageId>en</languageId><name>Greek</name></name>
    </names>
    <locales>
      <locale><localeId>el_GR.UTF-8</localeId><rank>900</rank></locale>
      <locale><localeId>el_CY.UTF-8</localeId><rank>100</rank></locale>
    </locales>
    <countries>
      <country><countryId>GR</countryId><rank>900</rank></country>
      <country><countryId>CY</countryId><rank>100</rank></country>
    </countries>
    <keyboards>
      <keyboard><keyboardId>gr</keyboardId><rank>1000</rank></keyboard>
    </keyboards>
    <timezones>
      <timezone><timezoneId>Europe/Athens</timezoneId><rank>900</rank></timezone>
      <timezone><timezoneId>Asia/Nicosia</timezoneId><rank>100</rank></timezone>
    </timezones>
  </language>
  <language>
    <languageId>en</languageId>
    <iso639-1>en</iso639-1>
    <iso639-2-t>eng</iso639-2-t>
    <iso639-2-b>eng</iso639-2-b>
    <names>
      <name><languageId>de</languageId><name>Englisch</name></name>
      <name><languageId>en</languageId><name>English</name></name>
    </names>
    <locales>
      <locale><localeId>en_US.UTF-8</localeId><rank>900</rank></locale>
      <locale><localeId>en_GB.UTF-8</localeId><rank>500</rank></locale>
      <locale><localeId>en_IN.UTF-8</localeId><rank>400</rank></locale>
      <locale><localeId>en_AU.UTF-8</localeId><rank>300</rank></locale>
      <locale><localeId>en_CA.UTF-8</localeId><rank>200</rank></locale>
      <locale><localeId>en_DK.UTF-8</localeId><rank>100</rank></locale>
      <locale><localeId>en_IE.UTF-8</localeId><rank>90</rank></locale>
      <locale><localeId>en_NZ.UTF-8</localeId><rank>80</rank></locale>
      <locale><localeId>en_NG.UTF-8</localeId><rank>70</rank></locale>
      <locale><localeId>en_HK.UTF-8</localeId><rank>60</rank></locale>
      <locale><localeId>en_PH.UTF-8</localeId><rank>50</rank></locale>
      <locale><localeId>en_SG.UTF-8</localeId><rank>40</rank></locale>
      <locale><localeId>en_ZA.UTF-8</localeId><rank>30</rank></locale>
      <locale><localeId>en_ZM.UTF-8</localeId><rank>25</rank></locale>
      <locale><localeId>en_ZW.UTF-8</localeId><rank>20</rank></locale>
      <locale><localeId>en_BW.UTF-8</localeId><rank>15</rank></locale>
      <locale><localeId>en_AG.UTF-8</localeId><rank>10</rank></locale>
    </locales>
    <countries>
      <country><countryId>US</countryId><rank>900</rank></country>
      <country><countryId>GB</countryId><rank>500</rank></country>
      <country><countryId>IN</countryId><rank>400</rank></country>
      <country><countryId>AU</countryId><rank>300</rank></country>
      <country><countryId>CA</countryId><rank>200</rank></country>
      <country><countryId>DK</countryId><rank>100</rank></country>
      <country><countryId>IE</countryId><rank>90</rank></country>
      <country><countryId>NZ</countryId><rank>80</rank></country>
      <country><countryId>NG</countryId><rank>70</rank></country>
      <country><countryId>HK</countryId><rank>60</rank></country>
      <country><countryId>PH</countryId><rank>50</rank></country>
      <country><countryId>SG</countryId><rank>40</rank></country>
      <country><countryId>ZA</countryId><rank>30</rank></country>
      <country><countryId>ZM</countryId><rank>25</rank></country>
      <country><countryId>ZW</countryId><rank>20</rank></country>
      <country><countryId>BW</countryId><rank>15</rank></country>
      <country><countryId>AG</countryId><rank>10</rank></country>
    </countries>
    <keyboards>
      <keyboard><keyboardId>us</keyboardId><rank>700</rank></keyboard>
      <keyboard><keyboardId>gb</keyboardId><rank>100</rank></keyboard>
    </keyboards>
    <timezones>
      <timezone><timezoneId>Australia/Melbourne</timezoneId><rank>100</rank></timezone>
      <timezone><timezoneId>Australia/Perth</timezoneId><rank>100</rank></timezone>
      <timezone><timezoneId>America/Edmonton</timezoneId><rank>100</rank></timezone>
      <timezone><timezoneId>Asia/Kolkata</timezoneId><rank>100</rank></timezone>
      <timezone><timezoneId>America/Denver</timezoneId><rank>100</rank></timezone>
      <timezone><timezoneId>Australia/Lord_Howe</timezoneId><rank>100</rank></timezone>
      <timezone><timezoneId>Australia/Sydney</timezoneId><rank>100</rank></timezone>
      <timezone><timezoneId>Africa/Johannesburg</timezoneId><rank>100</rank></timezone>
      <timezone><timezoneId>Australia/Darwin</timezoneId><rank>100</rank></timezone>
      <timezone><timezoneId>Africa/Gaborone</timezoneId><rank>100</rank></timezone>
      <timezone><timezoneId>Europe/London</timezoneId><rank>100</rank></timezone>
      <timezone><timezoneId>Europe/Copenhagen</timezoneId><rank>100</rank></timezone>
      <timezone><timezoneId>Asia/Singapore</timezoneId><rank>100</rank></timezone>
      <timezone><timezoneId>Australia/Currie</timezoneId><rank>100</rank></timezone>
      <timezone><timezoneId>Pacific/Honolulu</timezoneId><rank>100</rank></timezone>
      <timezone><timezoneId>Australia/Lindeman</timezoneId><rank>100</rank></timezone>
      <timezone><timezoneId>America/St_Johns</timezoneId><rank>100</rank></timezone>
      <timezone><timezoneId>America/Antigua</timezoneId><rank>100</rank></timezone>
      <timezone><timezoneId>America/Phoenix</timezoneId><rank>100</rank></timezone>
      <timezone><timezoneId>America/Winnipeg</timezoneId><rank>100</rank></timezone>
      <timezone><timezoneId>Australia/Brisbane</timezoneId><rank>100</rank></timezone>
      <timezone><timezoneId>America/Chicago</timezoneId><rank>100</rank></timezone>
      <timezone><timezoneId>America/Halifax</timezoneId><rank>100</rank></timezone>
      <timezone><timezoneId>Australia/Broken_Hill</timezoneId><rank>100</rank></timezone>
      <timezone><timezoneId>Asia/Hong_Kong</timezoneId><rank>100</rank></timezone>
      <timezone><timezoneId>Africa/Lusaka</timezoneId><rank>100</rank></timezone>
      <timezone><timezoneId>America/Los_Angeles</timezoneId><rank>100</rank></timezone>
      <timezone><timezoneId>America/New_York</timezoneId><rank>100</rank></timezone>
      <timezone><timezoneId>Europe/Dublin</timezoneId><rank>100</rank></timezone>
      <timezone><timezoneId>Africa/Lagos</timezoneId><rank>100</rank></timezone>
      <timezone><timezoneId>Australia/Hobart</timezoneId><rank>100</rank></timezone>
      <timezone><timezoneId>Australia/Adelaide</timezoneId><rank>100</rank></timezone>
      <timezone><timezoneId>America/Regina</timezoneId><rank>100</rank></timezone>
      <timezone><timezoneId>America/Vancouver</timezoneId><rank>100</rank></timezone>
      <timezone><timezoneId>America/Toronto</timezoneId><rank>100</rank></timezone>
      <timezone><timezoneId>Pacific/Auckland</timezoneId><rank>100</rank></timezone>
      <timezone><timezoneId>Australia/Eucla</timezoneId><rank>100</rank></timezone>
      <timezone><timezoneId>Pacific/Chatham</timezoneId><rank>100</rank></timezone>
      <timezone><timezoneId>America/Anchorage</timezoneId><rank>100</rank></timezone>
      <timezone><timezoneId>Asia/Manila</timezoneId><rank>100</rank></timezone>
      <timezone><timezoneId>Africa/Harare</timezoneId><rank>100</rank></timezone>
      <timezone><timezoneId>America/Nipigon</timezoneId><rank>1</rank></timezone>
      <timezone><timezoneId>America/Whitehorse</timezoneId><rank>1</rank></timezone>
      <timezone><timezoneId>America/Dawson_Creek</timezoneId><rank>1</rank></timezone>
      <timezone><timezoneId>America/Swift_Current</timezoneId><rank>1</rank></timezone>
      <timezone><timezoneId>America/Pangnirtung</timezoneId><rank>1</rank></timezone>
      <timezone><timezoneId>America/Resolute</timezoneId><rank>1</rank></timezone>
      <timezone><timezoneId>America/Moncton</timezoneId><rank>1</rank></timezone>
      <timezone><timezoneId>America/Dawson</timezoneId><rank>1</rank></timezone>
      <timezone><timezoneId>America/Blanc-Sablon</timezoneId><rank>1</rank></timezone>
      <timezone><timezoneId>America/Atikokan</timezoneId><rank>1</rank></timezone>
      <timezone><timezoneId>America/Glace_Bay</timezoneId><rank>1</rank></timezone>
      <timezone><timezoneId>America/Thunder_Bay</timezoneId><rank>1</rank></timezone>
      <timezone><timezoneId>America/Rainy_River</timezoneId><rank>1</rank></timezone>
      <timezone><timezoneId>America/Yellowknife</timezoneId><rank>1</rank></timezone>
      <timezone><timezoneId>America/Goose_Bay</timezoneId><rank>1</rank></timezone>
      <timezone><timezoneId>America/Inuvik</timezoneId><rank>1</rank></timezone>
      <timezone><timezoneId>America/Cambridge_Bay</timezoneId><rank>1</rank></timezone>
      <timezone><timezoneId>America/Montreal</timezoneId><rank>1</rank></timezone>
      <timezone><timezoneId>America/Rankin_Inlet</timezoneId><rank>1</rank></timezone>
      <timezone><timezoneId>America/Iqaluit</timezoneId><rank>1</rank></timezone>
    </timezones>
  </language>
  <language>
    <languageId>et</languageId>
    <iso639-1>et</iso639-1>
    <iso639-2-t>est</iso639-2-t>
    <iso639-2-b>est</iso639-2-b>
    <names>
      <name><languageId>de</languageId><name>Estnisch</name></name>
      <name><languageId>en</languageId><name>Estonian</name></name>
      <name><languageId>et</languageId><name>eesti</name></name>
    </names>
    <locales>
      <locale><localeId>et_EE.UTF-8</localeId><rank>1000</rank></locale>
    </locales>
    <countries>
      <country><countryId>EE</countryId><rank>1000</rank></country>
    </countries>
    <keyboards>
      <keyboard><keyboardId>ee</keyboardId><rank>1000</rank></keyboard>
    </keyboards>
    <timezones>
      <timezone><timezoneId>Europe/Tallinn</timezoneId><rank>1000</rank></timezone>
    </timezones>
  </language>
  <language>
    <languageId>fi</languageId>
    <iso639-1>fi</iso639-1>
    <iso639-2-t>fin</iso639-2-t>
    <iso639-2-b>fin</iso639-2-b>
    <names>
      <name><languageId>de</languageId><name>Finnisch</name></name>
      <name><languageId>en</languageId><name>Finnish</name></name>
      <name><languageId>fi</languageId><name>suomi</name></name>
    </names>
    <locales>
      <locale><localeId>fi_FI.UTF-8</localeId><rank>1000</rank></locale>
    </locales>
    <countries>
      <country><countryId>FI</countryId><rank>1000</rank></country>
    </countries>
    <keyboards>
      <keyboard><keyboardId>fi</keyboardId><rank>900</rank></keyboard>
      <keyboard><keyboardId>fi(nodeadkeys)</keyboardId><rank>100</rank></keyboard>
    </keyboards>
    <timezones>
      <timezone><timezoneId>Europe/Helsinki</timezoneId><rank>1000</rank></timezone>
    </timezones>
  </language>
  <language>
    <languageId>fr</languageId>
    <iso639-1>fr</iso639-1>
    <iso639-2-t>fra</iso639-2-t>
    <iso639-2-b>fre</iso639-2-b>
    <names>
      <name><languageId>de</languageId><name>Französisch</name></name>
      <name><languageId>en</languageId><name>French</name></name>
      <name><languageId>fr</languageId><name>français</name></name>
    </names>
    <locales>
      <locale><localeId>fr_FR.UTF-8</localeId><rank>500</rank></locale>
      <locale><localeId>fr_CA.UTF-8</localeId><rank>200</rank></locale>
      <locale><localeId>fr_BE.UTF-8</localeId><rank>100</rank></locale>
      <locale><localeId>fr_CH.UTF-8</localeId><rank>80</rank></locale>
      <locale><localeId>fr_LU.UTF-8</localeId><rank>20</rank></locale>
    </locales>
    <countries>
      <country><countryId>FR</countryId><rank>500</rank></country>
      <country><countryId>CA</countryId><rank>200</rank></country>
      <country><countryId>BE</countryId><rank>100</rank></country>
      <country><countryId>CH</countryId><rank>80</rank></country>
      <country><countryId>LU</countryId><rank>20</rank></country>
    </countries>
    <keyboards>
      <keyboard><keyboardId>fr(oss)</keyboardId><rank>600</rank></keyboard>
      <keyboard><keyboardId>ca</keyboardId><rank>300</rank></keyboard>
      <keyboard><keyboardId>ch(fr)</keyboardId><rank>100</rank></keyboard>
      <keyboard><keyboardId>fr</keyboardId><rank>0</rank></keyboard>
      <keyboard><keyboardId>fr(latin9)</keyboardId><rank>0</rank></keyboard>
    </keyboards>
    <timezones>
      <timezone><timezoneId>Europe/Paris</timezoneId><rank>300</rank></timezone>
      <timezone><timezoneId>America/Montreal</timezoneId><rank>200</rank></timezone>
      <timezone><timezoneId>Europe/Brussels</timezoneId><rank>100</rank></timezone>
      <timezone><timezoneId>Europe/Zurich</timezoneId><rank>50</rank></timezone>
      <timezone><timezoneId>Europe/Luxembourg</timezoneId><rank>20</rank></timezone>
    </timezones>
  </language>
  <language>
    <languageId>fur</languageId>
    <iso639-1>None</iso639-1>
    <iso639-2-t>fur</iso639-2-t>
    <iso639-2-b>fur</iso639-2-b>
    <names>
      <name><languageId>de</languageId><name>Friaulisch</name></name>
      <name><languageId>en</languageId><name>Friulian</name></name>
      <name><languageId>fur</languageId><name>furlan</name></name>
    </names>
    <locales>
      <locale><localeId>fur_IT.UTF-8</localeId><rank>1000</rank></locale>
    </locales>
    <countries>
      <country><countryId>IT</countryId><rank>1000</rank></country>
    </countries>
    <keyboards>
      <keyboard><keyboardId>it</keyboardId><rank>1000</rank></keyboard>
    </keyboards>
    <timezones>
      <timezone><timezoneId>Europe/Rome</timezoneId><rank>1000</rank></timezone>
    </timezones>
  </language>
  <language>
    <languageId>fy</languageId>
    <iso639-1>fy</iso639-1>
    <iso639-2-t>fry</iso639-2-t>
    <iso639-2-b>fry</iso639-2-b>
    <names>
      <name><languageId>de</languageId><name>Friesisch</name></name>
      <name><languageId>en</languageId><name>Western Frisian</name></name>
      <name><languageId>fy</languageId><name>Frysk</name></name>
    </names>
    <locales>
      <locale><localeId>fy_NL.UTF-8</localeId><rank>990</rank></locale>
      <locale><localeId>fy_DE.UTF-8</localeId><rank>10</rank></locale>
    </locales>
    <countries>
      <country><countryId>NL</countryId><rank>990</rank></country>
      <country><countryId>DE</countryId><rank>10</rank></country>
    </countries>
    <keyboards>
      <keyboard><keyboardId>us(euro)</keyboardId><rank>950</rank></keyboard>
      <keyboard><keyboardId>us(altgr-intl)</keyboardId><rank>50</rank></keyboard>
      <keyboard><keyboardId>nl</keyboardId><rank>0</rank></keyboard>
    </keyboards>
    <timezones>
      <timezone><timezoneId>Europe/Amsterdam</timezoneId><rank>1000</rank></timezone>
    </timezones>
  </language>
  <language>
    <languageId>gd</languageId>
    <iso639-1>gd</iso639-1>
    <iso639-2-t>gla</iso639-2-t>
    <iso639-2-b>gla</iso639-2-b>
    <names>
      <name><languageId>de</languageId><name>Schottisches Gälisch</name></name>
      <name><languageId>en</languageId><name>Scottish Gaelic</name></name>
      <name><languageId>gd</languageId><name>Gàidhlig</name></name>
    </names>
    <locales>
      <locale><localeId>gd_GB.UTF-8</localeId><rank>1000</rank></locale>
    </locales>
    <countries>
      <country><countryId>GB</countryId><rank>1000</rank></country>
    </countries>
    <keyboards>
      <keyboard><keyboardId>gb</keyboardId><rank>1000</rank></keyboard>
    </keyboards>
    <timezones>
      <timezone><timezoneId>Europe/London</timezoneId><rank>1000</rank></timezone>
    </timezones>
  </language>
  <language>
    <languageId>gl</languageId>
    <iso639-1>gl</iso639-1>
    <iso639-2-t>glg</iso639-2-t>
    <iso639-2-b>glg</iso639-2-b>
    <names>
      <name><languageId>de</languageId><name>Galizisch</name></name>
      <name><languageId>en</languageId><name>Galician</name></name>
      <name><languageId>gl</languageId><name>galego</name></name>
    </names>
    <locales>
      <locale><localeId>gl_ES.UTF-8</localeId><rank>1000</rank></locale>
    </locales>
    <countries>
      <country><countryId>ES</countryId><rank>1000</rank></country>
    </countries>
    <keyboards>
      <keyboard><keyboardId>es</keyboardId><rank>1000</rank></keyboard>
    </keyboards>
    <timezones>
      <timezone><timezoneId>Europe/Madrid</timezoneId><rank>1000</rank></timezone>
    </timezones>
  </language>
  <language>
    <languageId>gu</languageId>
    <iso639-1>gu</iso639-1>
    <iso639-2-t>guj</iso639-2-t>
    <iso639-2-b>guj</iso639-2-b>
    <names>
      <name><languageId>de</languageId><name>Gujarati</name></name>
      <name><languageId>en</languageId><name>Gujarati</name></name>
      <name><languageId>gu</languageId><name>ગુજરાતી</name></name>
    </names>
    <locales>
      <locale><localeId>gu_IN.UTF-8</localeId><rank>1000</rank></locale>
    </locales>
    <countries>
      <country><countryId>IN</countryId><rank>1000</rank></country>
    </countries>
    <keyboards>
      <keyboard><keyboardId>us</keyboardId><rank>1000</rank></keyboard>
    </keyboards>
    <timezones>
      <timezone><timezoneId>Asia/Kolkata</timezoneId><rank>1000</rank></timezone>
    </timezones>
  </language>
  <language>
    <languageId>gv</languageId>
    <iso639-1>gv</iso639-1>
    <iso639-2-t>glv</iso639-2-t>
    <iso639-2-b>glv</iso639-2-b>
    <names>
      <name><languageId>de</languageId><name>Manx</name></name>
      <name><languageId>en</languageId><name>Manx</name></name>
      <name><languageId>gv</languageId><name>Gaelg</name></name>
    </names>
    <locales>
      <locale><localeId>gv_GB.UTF-8</localeId><rank>1000</rank></locale>
    </locales>
    <countries>
      <country><countryId>GB</countryId><rank>1000</rank></country>
    </countries>
    <keyboards>
      <keyboard><keyboardId>gb</keyboardId><rank>1000</rank></keyboard>
    </keyboards>
    <timezones>
      <timezone><timezoneId>Europe/London</timezoneId><rank>1000</rank></timezone>
    </timezones>
  </language>
  <language>
    <languageId>hi</languageId>
    <iso639-1>hi</iso639-1>
    <iso639-2-t>hin</iso639-2-t>
    <iso639-2-b>hin</iso639-2-b>
    <names>
      <name><languageId>de</languageId><name>Hindi</name></name>
      <name><languageId>en</languageId><name>Hindi</name></name>
      <name><languageId>hi</languageId><name>हिन्दी</name></name>
    </names>
    <locales>
      <locale><localeId>hi_IN.UTF-8</localeId><rank>1000</rank></locale>
    </locales>
    <countries>
      <country><countryId>IN</countryId><rank>1000</rank></country>
    </countries>
    <keyboards>
      <keyboard><keyboardId>us</keyboardId><rank>1000</rank></keyboard>
    </keyboards>
    <timezones>
      <timezone><timezoneId>Asia/Kolkata</timezoneId><rank>1000</rank></timezone>
    </timezones>
  </language>
  <language>
    <languageId>hr</languageId>
    <iso639-1>hr</iso639-1>
    <iso639-2-t>hrv</iso639-2-t>
    <iso639-2-b>hrv</iso639-2-b>
    <names>
      <name><languageId>de</languageId><name>Kroatisch</name></name>
      <name><languageId>en</languageId><name>Croatian</name></name>
      <name><languageId>hr</languageId><name>hrvatski</name></name>
    </names>
    <locales>
      <locale><localeId>hr_HR.UTF-8</localeId><rank>1000</rank></locale>
    </locales>
    <countries>
      <country><countryId>HR</countryId><rank>1000</rank></country>
    </countries>
    <keyboards>
      <keyboard><keyboardId>hr</keyboardId><rank>1000</rank></keyboard>
    </keyboards>
    <timezones>
      <timezone><timezoneId>Europe/Zagreb</timezoneId><rank>1000</rank></timezone>
    </timezones>
  </language>
  <language>
    <languageId>ht</languageId>
    <iso639-1>ht</iso639-1>
    <iso639-2-t>hat</iso639-2-t>
    <iso639-2-b>hat</iso639-2-b>
    <names>
      <name><languageId>de</languageId><name>Haitianisch</name></name>
      <name><languageId>en</languageId><name>Haitian</name></name>
      <name><languageId>es</languageId><name>haitiano</name></name>
      <name><languageId>fr</languageId><name>haïtien</name></name>
      <name><languageId>ht</languageId><name>Kreyòl ayisyen</name></name>
    </names>
    <locales>
      <locale><localeId>ht_HT.UTF-8</localeId><rank>1000</rank></locale>
    </locales>
    <countries>
      <country><countryId>HT</countryId><rank>1000</rank></country>
    </countries>
    <keyboards>
      <keyboard><keyboardId>latam</keyboardId><rank>1000</rank></keyboard>
    </keyboards>
    <timezones>
      <timezone><timezoneId>America/Port-au-Prince</timezoneId><rank>1000</rank></timezone>
    </timezones>
  </language>
  <language>
    <languageId>hu</languageId>
    <iso639-1>hu</iso639-1>
    <iso639-2-t>hun</iso639-2-t>
    <iso639-2-b>hun</iso639-2-b>
    <names>
      <name><languageId>de</languageId><name>Ungarisch</name></name>
      <name><languageId>en</languageId><name>Hungarian</name></name>
      <name><languageId>hu</languageId><name>magyar</name></name>
    </names>
    <locales>
      <locale><localeId>hu_HU.UTF-8</localeId><rank>1000</rank></locale>
    </locales>
    <countries>
      <country><countryId>HU</countryId><rank>1000</rank></country>
    </countries>
    <keyboards>
      <keyboard><keyboardId>hu</keyboardId><rank>1000</rank></keyboard>
    </keyboards>
    <timezones>
      <timezone><timezoneId>Europe/Budapest</timezoneId><rank>1000</rank></timezone>
    </timezones>
  </language>
  <language>
    <languageId>id</languageId>
    <iso639-1>id</iso639-1>
    <iso639-2-t>ind</iso639-2-t>
    <iso639-2-b>ind</iso639-2-b>
    <names>
      <name><languageId>de</languageId><name>Indonesisch</name></name>
      <name><languageId>en</languageId><name>Indonesian</name></name>
      <name><languageId>id</languageId><name>Bahasa Indonesia</name></name>
    </names>
    <locales>
      <locale><localeId>id_ID.UTF-8</localeId><rank>1000</rank></locale>
    </locales>
    <countries>
      <country><countryId>ID</countryId><rank>1000</rank></country>
    </countries>
    <keyboards>
      <keyboard><keyboardId>us</keyboardId><rank>1000</rank></keyboard>
    </keyboards>
    <timezones>
      <timezone><timezoneId>Asia/Jayapura</timezoneId><rank>1000</rank></timezone>
    </timezones>
  </language>
  <language>
    <languageId>is</languageId>
    <iso639-1>is</iso639-1>
    <iso639-2-t>isl</iso639-2-t>
    <iso639-2-b>ice</iso639-2-b>
    <names>
      <name><languageId>de</languageId><name>Isländisch</name></name>
      <name><languageId>en</languageId><name>Icelandic</name></name>
      <name><languageId>is</languageId><name>íslenska</name></name>
    </names>
    <locales>
      <locale><localeId>is_IS.UTF-8</localeId><rank>1000</rank></locale>
    </locales>
    <countries>
      <country><countryId>IS</countryId><rank>1000</rank></country>
    </countries>
    <keyboards>
      <keyboard><keyboardId>is</keyboardId><rank>1000</rank></keyboard>
    </keyboards>
    <timezones>
      <timezone><timezoneId>Atlantic/Reykjavik</timezoneId><rank>1000</rank></timezone>
    </timezones>
  </language>
  <language>
    <languageId>it</languageId>
    <iso639-1>it</iso639-1>
    <iso639-2-t>ita</iso639-2-t>
    <iso639-2-b>ita</iso639-2-b>
    <names>
      <name><languageId>de</languageId><name>Italienisch</name></name>
      <name><languageId>en</languageId><name>Italian</name></name>
      <name><languageId>it</languageId><name>italiano</name></name>
    </names>
    <locales>
      <locale><localeId>it_IT.UTF-8</localeId><rank>900</rank></locale>
      <locale><localeId>it_CH.UTF-8</localeId><rank>100</rank></locale>
    </locales>
    <countries>
      <country><countryId>IT</countryId><rank>900</rank></country>
      <country><countryId>CH</countryId><rank>100</rank></country>
    </countries>
    <keyboards>
      <keyboard><keyboardId>it</keyboardId><rank>1000</rank></keyboard>
    </keyboards>
    <timezones>
      <timezone><timezoneId>Europe/Rome</timezoneId><rank>900</rank></timezone>
      <timezone><timezoneId>Europe/Zurich</timezoneId><rank>100</rank></timezone>
    </timezones>
  </language>
  <language>
    <languageId>ja</languageId>
    <iso639-1>ja</iso639-1>
    <iso639-2-t>jpn</iso639-2-t>
    <iso639-2-b>jpn</iso639-2-b>
    <names>
      <name><languageId>de</languageId><name>Japanisch</name></name>
      <name><languageId>en</languageId><name>Japanese</name></name>
      <name><languageId>ja</languageId><name>日本語</name></name>
    </names>
    <locales>
      <locale><localeId>ja_JP.UTF-8</localeId><rank>1000</rank></locale>
    </locales>
    <countries>
      <country><countryId>JP</countryId><rank>1000</rank></country>
    </countries>
    <keyboards>
      <keyboard><keyboardId>jp</keyboardId><rank>1000</rank></keyboard>
    </keyboards>
    <timezones>
      <timezone><timezoneId>Asia/Tokyo</timezoneId><rank>1000</rank></timezone>
    </timezones>
  </language>
  <language>
    <languageId>kn</languageId>
    <iso639-1>kn</iso639-1>
    <iso639-2-t>kan</iso639-2-t>
    <iso639-2-b>kan</iso639-2-b>
    <names>
      <name><languageId>de</languageId><name>Kannada</name></name>
      <name><languageId>en</languageId><name>Kannada</name></name>
      <name><languageId>kn</languageId><name>ಕನ್ನಡ</name></name>
    </names>
    <locales>
      <locale><localeId>kn_IN.UTF-8</localeId><rank>1000</rank></locale>
    </locales>
    <countries>
      <country><countryId>IN</countryId><rank>1000</rank></country>
    </countries>
    <keyboards>
      <keyboard><keyboardId>us</keyboardId><rank>1000</rank></keyboard>
    </keyboards>
    <timezones>
      <timezone><timezoneId>Asia/Kolkata</timezoneId><rank>1000</rank></timezone>
    </timezones>
  </language>
  <language>
    <languageId>ko</languageId>
    <iso639-1>ko</iso639-1>
    <iso639-2-t>kor</iso639-2-t>
    <iso639-2-b>kor</iso639-2-b>
    <names>
      <name><languageId>de</languageId><name>Koreanisch</name></name>
      <name><languageId>en</languageId><name>Korean</name></name>
      <name><languageId>ko</languageId><name>한국어</name></name>
    </names>
    <locales>
      <locale><localeId>ko_KR.UTF-8</localeId><rank>1000</rank></locale>
    </locales>
    <countries>
      <country><countryId>KR</countryId><rank>1000</rank></country>
    </countries>
    <keyboards>
      <keyboard><keyboardId>kr</keyboardId><rank>1000</rank></keyboard>
    </keyboards>
    <timezones>
      <timezone><timezoneId>Asia/Seoul</timezoneId><rank>1000</rank></timezone>
    </timezones>
  </language>
  <language>
    <languageId>ku</languageId>
    <iso639-1>ku</iso639-1>
    <iso639-2-t>kur</iso639-2-t>
    <iso639-2-b>kur</iso639-2-b>
    <names>
      <name><languageId>de</languageId><name>Kurdisch</name></name>
      <name><languageId>en</languageId><name>Kurdish</name></name>
      <name><languageId>ku</languageId><name>Kurdî</name></name>
    </names>
    <locales>
      <locale><localeId>ku_TR.UTF-8</localeId><rank>1000</rank></locale>
    </locales>
    <countries>
      <country><countryId>TR</countryId><rank>1000</rank></country>
    </countries>
    <keyboards>
      <keyboard><keyboardId>tr(ku)</keyboardId><rank>1000</rank></keyboard>
    </keyboards>
    <timezones>
      <timezone><timezoneId>Europe/Istanbul</timezoneId><rank>1000</rank></timezone>
    </timezones>
  </language>
  <language>
    <languageId>kw</languageId>
    <iso639-1>kw</iso639-1>
    <iso639-2-t>cor</iso639-2-t>
    <iso639-2-b>cor</iso639-2-b>
    <names>
      <name><languageId>de</languageId><name>Kornisch</name></name>
      <name><languageId>en</languageId><name>Cornish</name></name>
      <name><languageId>kw</languageId><name>kernewek</name></name>
    </names>
    <locales>
      <locale><localeId>kw_GB.UTF-8</localeId><rank>1000</rank></locale>
    </locales>
    <countries>
      <country><countryId>GB</countryId><rank>1000</rank></country>
    </countries>
    <keyboards>
      <keyboard><keyboardId>gb</keyboardId><rank>1000</rank></keyboard>
    </keyboards>
    <timezones>
      <timezone><timezoneId>Europe/London</timezoneId><rank>1000</rank></timezone>
    </timezones>
  </language>
  <language>
    <languageId>li</languageId>
    <iso639-1>li</iso639-1>
    <iso639-2-t>lim</iso639-2-t>
    <iso639-2-b>lim</iso639-2-b>
    <names>
      <name><languageId>de</languageId><name>Limburgisch</name></name>
      <name><languageId>en</languageId><name>Limburgish</name></name>
      <name><languageId>li</languageId><name>Lèmbörgs</name></name>
    </names>
    <locales>
      <locale><localeId>li_NL.UTF-8</localeId><rank>501</rank></locale>
      <locale><localeId>li_BE.UTF-8</localeId><rank>499</rank></locale>
    </locales>
    <countries>
      <country><countryId>NL</countryId><rank>501</rank></country>
      <country><countryId>BE</countryId><rank>499</rank></country>
    </countries>
    <keyboards>
      <keyboard><keyboardId>us(euro)</keyboardId><rank>950</rank></keyboard>
      <keyboard><keyboardId>us(altgr-intl)</keyboardId><rank>50</rank></keyboard>
      <keyboard><keyboardId>be(oss)</keyboardId><rank>1</rank></keyboard>
      <keyboard><keyboardId>nl</keyboardId><rank>0</rank></keyboard>
    </keyboards>
    <timezones>
      <timezone><timezoneId>Europe/Amsterdam</timezoneId><rank>501</rank></timezone>
      <timezone><timezoneId>Europe/Brussels</timezoneId><rank>499</rank></timezone>
    </timezones>
  </language>
  <language>
    <languageId>lij</languageId>
    <iso639-1>None</iso639-1>
    <iso639-2-t>None</iso639-2-t>
    <iso639-2-b>None</iso639-2-b>
    <names>
      <name><languageId>de</languageId><name>Ligurisch</name></name>
      <name><languageId>en</languageId><name>Ligurian</name></name>
      <name><languageId>lij</languageId><name>Lìgure</name></name>
    </names>
    <locales>
      <locale><localeId>lij_IT.UTF-8</localeId><rank>1000</rank></locale>
    </locales>
    <countries>
      <country><countryId>IT</countryId><rank>1000</rank></country>
    </countries>
    <keyboards>
      <keyboard><keyboardId>it</keyboardId><rank>1000</rank></keyboard>
    </keyboards>
    <timezones>
      <timezone><timezoneId>Europe/Rome</timezoneId><rank>1000</rank></timezone>
    </timezones>
  </language>
  <language>
    <languageId>mk</languageId>
    <iso639-1>mk</iso639-1>
    <iso639-2-t>mkd</iso639-2-t>
    <iso639-2-b>mac</iso639-2-b>
    <names>
      <name><languageId>de</languageId><name>Mazedonisch</name></name>
      <name><languageId>en</languageId><name>Macedonian</name></name>
      <name><languageId>mk</languageId><name>македонски</name></name>
    </names>
    <locales>
      <locale><localeId>mk_MK.UTF-8</localeId><rank>1000</rank></locale>
    </locales>
    <countries>
      <country><countryId>MK</countryId><rank>1000</rank></country>
    </countries>
    <keyboards>
      <keyboard><keyboardId>mk</keyboardId><rank>1000</rank></keyboard>
    </keyboards>
    <timezones>
      <timezone><timezoneId>Europe/Skopje</timezoneId><rank>1000</rank></timezone>
    </timezones>
  </language>
  <language>
    <languageId>ml</languageId>
    <iso639-1>ml</iso639-1>
    <iso639-2-t>mal</iso639-2-t>
    <iso639-2-b>mal</iso639-2-b>
    <names>
      <name><languageId>de</languageId><name>Malayalam</name></name>
      <name><languageId>en</languageId><name>Malayalam</name></name>
      <name><languageId>ml</languageId><name>മലയാളം</name></name>
    </names>
    <locales>
      <locale><localeId>ml_IN.UTF-8</localeId><rank>1000</rank></locale>
    </locales>
    <countries>
      <country><countryId>IN</countryId><rank>1000</rank></country>
    </countries>
    <keyboards>
      <keyboard><keyboardId>us</keyboardId><rank>1000</rank></keyboard>
    </keyboards>
    <timezones>
      <timezone><timezoneId>Asia/Kolkata</timezoneId><rank>1000</rank></timezone>
    </timezones>
  </language>
  <language>
    <languageId>mr</languageId>
    <iso639-1>mr</iso639-1>
    <iso639-2-t>mar</iso639-2-t>
    <iso639-2-b>mar</iso639-2-b>
    <names>
      <name><languageId>de</languageId><name>Marathi</name></name>
      <name><languageId>en</languageId><name>Marathi</name></name>
      <name><languageId>mr</languageId><name>मराठी</name></name>
    </names>
    <locales>
      <locale><localeId>mr_IN.UTF-8</localeId><rank>1000</rank></locale>
    </locales>
    <countries>
      <country><countryId>IN</countryId><rank>1000</rank></country>
    </countries>
    <keyboards>
      <keyboard><keyboardId>us</keyboardId><rank>1000</rank></keyboard>
    </keyboards>
    <timezones>
      <timezone><timezoneId>Asia/Kolkata</timezoneId><rank>1000</rank></timezone>
    </timezones>
  </language>
  <language>
    <languageId>ms</languageId>
    <iso639-1>ms</iso639-1>
    <iso639-2-t>msa</iso639-2-t>
    <iso639-2-b>may</iso639-2-b>
    <names>
      <name><languageId>de</languageId><name>Malaiisch</name></name>
      <name><languageId>en</languageId><name>Malay</name></name>
      <name><languageId>sq</languageId><name>Bahasa Melayu</name></name>
    </names>
    <locales>
      <locale><localeId>ms_MY_AL.UTF-8</localeId><rank>1000</rank></locale>
    </locales>
    <countries>
      <country><countryId>MY</countryId><rank>1000</rank></country>
    </countries>
    <keyboards>
      <keyboard><keyboardId>us</keyboardId><rank>1000</rank></keyboard>
    </keyboards>
    <timezones>
      <timezone><timezoneId>Asia/Kuala_Lumpur</timezoneId><rank>800</rank></timezone>
      <timezone><timezoneId>Asia/Kuching</timezoneId><rank>200</rank></timezone>
    </timezones>
  </language>
  <language>
    <languageId>nb</languageId>
    <iso639-1>nb</iso639-1>
    <iso639-2-t>nob</iso639-2-t>
    <iso639-2-b>nob</iso639-2-b>
    <names>
      <name><languageId>de</languageId><name>Norwegisch Bokmål</name></name>
      <name><languageId>en</languageId><name>Norwegian Bokmål</name></name>
      <name><languageId>nb</languageId><name>norsk bokmål</name></name>
      <name><languageId>nn</languageId><name>bokmål</name></name>
    </names>
    <locales>
      <locale><localeId>nb_NO.UTF-8</localeId><rank>1000</rank></locale>
    </locales>
    <countries>
      <country><countryId>NO</countryId><rank>1000</rank></country>
    </countries>
    <keyboards>
      <keyboard><keyboardId>no</keyboardId><rank>1000</rank></keyboard>
    </keyboards>
    <timezones>
      <timezone><timezoneId>Europe/Oslo</timezoneId><rank>1000</rank></timezone>
    </timezones>
  </language>
  <language>
    <languageId>nds</languageId>
    <iso639-1>None</iso639-1>
    <iso639-2-t>nds</iso639-2-t>
    <iso639-2-b>nds</iso639-2-b>
    <names>
      <name><languageId>de</languageId><name>Plattdeutsch</name></name>
      <name><languageId>en</languageId><name>Low German</name></name>
      <name><languageId>nds</languageId><name>Plattdüütsch</name></name>
      <name><languageId>nl</languageId><name>Nederduits</name></name>
    </names>
    <locales>
      <locale><localeId>nds_NL.UTF-8</localeId><rank>900</rank></locale>
      <locale><localeId>nds_DE.UTF-8</localeId><rank>100</rank></locale>
    </locales>
    <countries>
      <country><countryId>NL</countryId><rank>900</rank></country>
      <country><countryId>DE</countryId><rank>100</rank></country>
    </countries>
    <keyboards>
      <keyboard><keyboardId>us(euro)</keyboardId><rank>950</rank></keyboard>
      <keyboard><keyboardId>us(altgr-intl)</keyboardId><rank>50</rank></keyboard>
      <keyboard><keyboardId>nl</keyboardId><rank>0</rank></keyboard>
    </keyboards>
    <timezones>
      <timezone><timezoneId>Europe/Amsterdam</timezoneId><rank>900</rank></timezone>
      <timezone><timezoneId>Europe/Berlin</timezoneId><rank>100</rank></timezone>
    </timezones>
  </language>
  <language>
    <languageId>nl</languageId>
    <iso639-1>nl</iso639-1>
    <iso639-2-t>nld</iso639-2-t>
    <iso639-2-b>dut</iso639-2-b>
    <names>
      <name><languageId>de</languageId><name>Niederländisch</name></name>
      <name><languageId>en</languageId><name>Dutch</name></name>
      <name><languageId>nl</languageId><name>Nederlands</name></name>
    </names>
    <locales>
      <locale><localeId>nl_NL.UTF-8</localeId><rank>800</rank></locale>
      <locale><localeId>nl_BE.UTF-8</localeId><rank>100</rank></locale>
      <locale><localeId>nl_AW.UTF-8</localeId><rank>50</rank></locale>
    </locales>
    <countries>
      <country><countryId>NL</countryId><rank>800</rank></country>
      <country><countryId>BE</countryId><rank>100</rank></country>
      <country><countryId>AW</countryId><rank>50</rank></country>
    </countries>
    <keyboards>
      <keyboard><keyboardId>us(euro)</keyboardId><rank>950</rank></keyboard>
      <keyboard><keyboardId>us(altgr-intl)</keyboardId><rank>50</rank></keyboard>
      <keyboard><keyboardId>nl</keyboardId><rank>0</rank></keyboard>
    </keyboards>
    <timezones>
      <timezone><timezoneId>Europe/Amsterdam</timezoneId><rank>800</rank></timezone>
      <timezone><timezoneId>Europe/Brussels</timezoneId><rank>100</rank></timezone>
      <timezone><timezoneId>America/Aruba</timezoneId><rank>50</rank></timezone>
    </timezones>
  </language>
  <language>
    <languageId>nn</languageId>
    <iso639-1>nn</iso639-1>
    <iso639-2-t>nno</iso639-2-t>
    <iso639-2-b>nno</iso639-2-b>
    <names>
      <name><languageId>de</languageId><name>Norwegisch Nynorsk</name></name>
      <name><languageId>en</languageId><name>Norwegian Nynorsk</name></name>
      <name><languageId>nb</languageId><name>norsk nynorsk</name></name>
      <name><languageId>nn</languageId><name>nynorsk</name></name>
    </names>
    <locales>
      <locale><localeId>nn_NO.UTF-8</localeId><rank>1000</rank></locale>
    </locales>
    <countries>
      <country><countryId>NO</countryId><rank>1000</rank></country>
    </countries>
    <keyboards>
      <keyboard><keyboardId>no</keyboardId><rank>1000</rank></keyboard>
    </keyboards>
    <timezones>
      <timezone><timezoneId>Europe/Oslo</timezoneId><rank>1000</rank></timezone>
    </timezones>
  </language>
  <language>
    <languageId>nso</languageId>
    <iso639-1>None</iso639-1>
    <iso639-2-t>nso</iso639-2-t>
    <iso639-2-b>nso</iso639-2-b>
    <names>
      <name><languageId>de</languageId><name>Nord-Sotho-Sprache</name></name>
      <name><languageId>en</languageId><name>Northern Sotho</name></name>
      <name><languageId>nso</languageId><name>Sesotho sa Leboa</name></name>
    </names>
    <locales>
      <locale><localeId>nso_ZA.UTF-8</localeId><rank>1000</rank></locale>
    </locales>
    <countries>
      <country><countryId>ZA</countryId><rank>1000</rank></country>
    </countries>
    <keyboards>
      <keyboard><keyboardId>us</keyboardId><rank>1000</rank></keyboard>
    </keyboards>
    <timezones>
      <timezone><timezoneId>Africa/Johannesburg</timezoneId><rank>1000</rank></timezone>
    </timezones>
  </language>
  <language>
    <languageId>or</languageId>
    <iso639-1>or</iso639-1>
    <iso639-2-t>ori</iso639-2-t>
    <iso639-2-b>ori</iso639-2-b>
    <names>
      <name><languageId>de</languageId><name>Orija</name></name>
      <name><languageId>en</languageId><name>Oriya</name></name>
      <name><languageId>or</languageId><name>ଓଡ଼ିଆ</name></name>
    </names>
    <locales>
      <locale><localeId>or_IN.UTF-8</localeId><rank>1000</rank></locale>
    </locales>
    <countries>
      <country><countryId>IN</countryId><rank>1000</rank></country>
    </countries>
    <keyboards>
      <keyboard><keyboardId>us</keyboardId><rank>1000</rank></keyboard>
    </keyboards>
    <timezones>
      <timezone><timezoneId>Asia/Kolkata</timezoneId><rank>1000</rank></timezone>
    </timezones>
  </language>
  <language>
    <languageId>pa</languageId>
    <iso639-1>pa</iso639-1>
    <iso639-2-t>pan</iso639-2-t>
    <iso639-2-b>pan</iso639-2-b>
    <names>
      <name><languageId>de</languageId><name>Panjabi</name></name>
      <name><languageId>en</languageId><name>Punjabi</name></name>
      <name><languageId>par</languageId><name>ਪੰਜਾਬੀ</name></name>
    </names>
    <locales>
      <locale><localeId>pa_PK.UTF-8</localeId><rank>600</rank></locale>
      <locale><localeId>pa_IN.UTF-8</localeId><rank>400</rank></locale>
    </locales>
    <countries>
      <country><countryId>PK</countryId><rank>600</rank></country>
      <country><countryId>IN</countryId><rank>400</rank></country>
    </countries>
    <keyboards>
      <keyboard><keyboardId>us</keyboardId><rank>1000</rank></keyboard>
    </keyboards>
    <timezones>
      <timezone><timezoneId>Asia/Karachi</timezoneId><rank>600</rank></timezone>
      <timezone><timezoneId>Asia/Kolkata</timezoneId><rank>400</rank></timezone>
    </timezones>
  </language>
  <language>
    <languageId>pl</languageId>
    <iso639-1>pl</iso639-1>
    <iso639-2-t>pol</iso639-2-t>
    <iso639-2-b>pol</iso639-2-b>
    <names>
      <name><languageId>de</languageId><name>Polnisch</name></name>
      <name><languageId>en</languageId><name>Polish</name></name>
      <name><languageId>pl</languageId><name>polski</name></name>
    </names>
    <locales>
      <locale><localeId>pl_PL.UTF-8</localeId><rank>1000</rank></locale>
    </locales>
    <countries>
      <country><countryId>PL</countryId><rank>1000</rank></country>
    </countries>
    <keyboards>
      <keyboard><keyboardId>pl</keyboardId><rank>1000</rank></keyboard>
    </keyboards>
    <timezones>
      <timezone><timezoneId>Europe/Warsaw</timezoneId><rank>1000</rank></timezone>
    </timezones>
  </language>
  <language>
    <languageId>pt</languageId>
    <iso639-1>pt</iso639-1>
    <iso639-2-t>por</iso639-2-t>
    <iso639-2-b>por</iso639-2-b>
    <names>
      <name><languageId>de</languageId><name>Portugiesisch</name></name>
      <name><languageId>en</languageId><name>Portuguese</name></name>
      <name><languageId>pt</languageId><name>português</name></name>
    </names>
    <locales>
      <locale><localeId>pt_BR.UTF-8</localeId><rank>600</rank></locale>
      <locale><localeId>pt_PT.UTF-8</localeId><rank>400</rank></locale>
    </locales>
    <countries>
      <country><countryId>BR</countryId><rank>600</rank></country>
      <country><countryId>PT</countryId><rank>400</rank></country>
    </countries>
    <keyboards>
      <keyboard><keyboardId>br</keyboardId><rank>600</rank></keyboard>
      <keyboard><keyboardId>pt</keyboardId><rank>400</rank></keyboard>
    </keyboards>
    <timezones>
      <timezone><timezoneId>America/Fortaleza</timezoneId><rank>1000</rank></timezone>
      <timezone><timezoneId>America/Cuiaba</timezoneId><rank>1000</rank></timezone>
      <timezone><timezoneId>America/Manaus</timezoneId><rank>1000</rank></timezone>
      <timezone><timezoneId>America/Bahia</timezoneId><rank>1000</rank></timezone>
      <timezone><timezoneId>America/Noronha</timezoneId><rank>1000</rank></timezone>
      <timezone><timezoneId>America/Sao_Paulo</timezoneId><rank>1000</rank></timezone>
      <timezone><timezoneId>Europe/Lisbon</timezoneId><rank>900</rank></timezone>
      <timezone><timezoneId>Atlantic/Azores</timezoneId><rank>100</rank></timezone>
      <timezone><timezoneId>Atlantic/Madeira</timezoneId><rank>100</rank></timezone>
      <timezone><timezoneId>America/Boa_Vista</timezoneId><rank>1</rank></timezone>
      <timezone><timezoneId>America/Araguaina</timezoneId><rank>1</rank></timezone>
      <timezone><timezoneId>America/Belem</timezoneId><rank>1</rank></timezone>
      <timezone><timezoneId>America/Porto_Velho</timezoneId><rank>1</rank></timezone>
      <timezone><timezoneId>America/Maceio</timezoneId><rank>1</rank></timezone>
      <timezone><timezoneId>America/Eirunepe</timezoneId><rank>1</rank></timezone>
      <timezone><timezoneId>America/Rio_Branco</timezoneId><rank>1</rank></timezone>
      <timezone><timezoneId>America/Recife</timezoneId><rank>1</rank></timezone>
      <timezone><timezoneId>America/Santarem</timezoneId><rank>1</rank></timezone>
      <timezone><timezoneId>America/Campo_Grande</timezoneId><rank>1</rank></timezone>
    </timezones>
  </language>
  <language>
    <languageId>ru</languageId>
    <iso639-1>ru</iso639-1>
    <iso639-2-t>rus</iso639-2-t>
    <iso639-2-b>rus</iso639-2-b>
    <names>
      <name><languageId>de</languageId><name>Russisch</name></name>
      <name><languageId>en</languageId><name>Russian</name></name>
      <name><languageId>ru</languageId><name>русский</name></name>
    </names>
    <locales>
      <locale><localeId>ru_RU.UTF-8</localeId><rank>800</rank></locale>
      <locale><localeId>ru_UA.UTF-8</localeId><rank>100</rank></locale>
    </locales>
    <countries>
      <country><countryId>RU</countryId><rank>800</rank></country>
      <country><countryId>UA</countryId><rank>100</rank></country>
    </countries>
    <keyboards>
      <keyboard><keyboardId>ru</keyboardId><rank>1000</rank></keyboard>
    </keyboards>
    <timezones>
      <timezone><timezoneId>Europe/Moscow</timezoneId><rank>300</rank></timezone>
      <timezone><timezoneId>Europe/Kaliningrad</timezoneId><rank>50</rank></timezone>
      <timezone><timezoneId>Europe/Volgograd</timezoneId><rank>49</rank></timezone>
      <timezone><timezoneId>Europe/Samara</timezoneId><rank>48</rank></timezone>
      <timezone><timezoneId>Asia/Yekaterinburg</timezoneId><rank>47</rank></timezone>
      <timezone><timezoneId>Asia/Omsk</timezoneId><rank>46</rank></timezone>
      <timezone><timezoneId>Asia/Novosibirsk</timezoneId><rank>45</rank></timezone>
      <timezone><timezoneId>Asia/Novokuznetsk</timezoneId><rank>44</rank></timezone>
      <timezone><timezoneId>Asia/Krasnoyarsk</timezoneId><rank>43</rank></timezone>
      <timezone><timezoneId>Asia/Irkutsk</timezoneId><rank>42</rank></timezone>
      <timezone><timezoneId>Asia/Yakutsk</timezoneId><rank>41</rank></timezone>
      <timezone><timezoneId>Asia/Khandyga</timezoneId><rank>40</rank></timezone>
      <timezone><timezoneId>Asia/Vladivostok</timezoneId><rank>39</rank></timezone>
      <timezone><timezoneId>Asia/Sakhalin</timezoneId><rank>38</rank></timezone>
      <timezone><timezoneId>Asia/Ust-Nera</timezoneId><rank>37</rank></timezone>
      <timezone><timezoneId>Asia/Magadan</timezoneId><rank>36</rank></timezone>
      <timezone><timezoneId>Asia/Kamchatka</timezoneId><rank>35</rank></timezone>
      <timezone><timezoneId>Asia/Anadyr</timezoneId><rank>34</rank></timezone>
    </timezones>
  </language>
  <language>
    <languageId>sc</languageId>
    <iso639-1>sc</iso639-1>
    <iso639-2-t>srd</iso639-2-t>
    <iso639-2-b>srd</iso639-2-b>
    <names>
      <name><languageId>de</languageId><name>Sardisch</name></name>
      <name><languageId>en</languageId><name>Sardinian</name></name>
      <name><languageId>sc</languageId><name>sardu</name></name>
    </names>
    <locales>
      <locale><localeId>sc_IT.UTF-8</localeId><rank>1000</rank></locale>
    </locales>
    <countries>
      <country><countryId>IT</countryId><rank>1000</rank></country>
    </countries>
    <keyboards>
      <keyboard><keyboardId>it</keyboardId><rank>1000</rank></keyboard>
    </keyboards>
    <timezones>
      <timezone><timezoneId>Europe/Rome</timezoneId><rank>1000</rank></timezone>
    </timezones>
  </language>
  <language>
    <languageId>se</languageId>
    <iso639-1>se</iso639-1>
    <iso639-2-t>sme</iso639-2-t>
    <iso639-2-b>sme</iso639-2-b>
    <names>
      <name><languageId>de</languageId><name>Nord-Samisch</name></name>
      <name><languageId>en</languageId><name>Northern Sami</name></name>
      <name><languageId>se</languageId><name>Davvisámegiella</name></name>
    </names>
    <locales>
      <locale><localeId>se_NO.UTF-8</localeId><rank>1000</rank></locale>
    </locales>
    <countries>
      <country><countryId>NO</countryId><rank>1000</rank></country>
    </countries>
    <keyboards>
      <keyboard><keyboardId>no</keyboardId><rank>1000</rank></keyboard>
    </keyboards>
    <timezones>
      <timezone><timezoneId>Europe/Oslo</timezoneId><rank>1000</rank></timezone>
    </timezones>
  </language>
  <language>
    <languageId>si</languageId>
    <iso639-1>si</iso639-1>
    <iso639-2-t>sin</iso639-2-t>
    <iso639-2-b>sin</iso639-2-b>
    <names>
      <name><languageId>de</languageId><name>Singhalesisch</name></name>
      <name><languageId>en</languageId><name>Sinhala</name></name>
      <name><languageId>si</languageId><name>සිංහල</name></name>
    </names>
    <locales>
      <locale><localeId>te_LK.UTF-8</localeId><rank>1000</rank></locale>
    </locales>
    <countries>
      <country><countryId>LK</countryId><rank>1000</rank></country>
    </countries>
    <keyboards>
      <keyboard><keyboardId>us</keyboardId><rank>1000</rank></keyboard>
    </keyboards>
    <timezones>
      <timezone><timezoneId>Asia/Colombo</timezoneId><rank>1000</rank></timezone>
    </timezones>
  </language>
  <language>
    <languageId>sk</languageId>
    <iso639-1>sk</iso639-1>
    <iso639-2-t>slk</iso639-2-t>
    <iso639-2-b>slo</iso639-2-b>
    <names>
      <name><languageId>de</languageId><name>Slowakisch</name></name>
      <name><languageId>en</languageId><name>Slovak</name></name>
      <name><languageId>sk</languageId><name>slovenčina</name></name>
    </names>
    <locales>
      <locale><localeId>sk_SK.UTF-8</localeId><rank>1000</rank></locale>
    </locales>
    <countries>
      <country><countryId>SK</countryId><rank>1000</rank></country>
    </countries>
    <keyboards>
      <keyboard><keyboardId>sk</keyboardId><rank>1000</rank></keyboard>
    </keyboards>
    <timezones>
      <timezone><timezoneId>Europe/Bratislava</timezoneId><rank>1000</rank></timezone>
    </timezones>
  </language>
  <language>
    <languageId>sl</languageId>
    <iso639-1>sl</iso639-1>
    <iso639-2-t>slv</iso639-2-t>
    <iso639-2-b>slv</iso639-2-b>
    <names>
      <name><languageId>de</languageId><name>Slowenisch</name></name>
      <name><languageId>en</languageId><name>Slovenian</name></name>
      <name><languageId>sl</languageId><name>slovenščina</name></name>
    </names>
    <locales>
      <locale><localeId>sl_SI.UTF-8</localeId><rank>1000</rank></locale>
    </locales>
    <countries>
      <country><countryId>SI</countryId><rank>1000</rank></country>
    </countries>
    <keyboards>
      <keyboard><keyboardId>si</keyboardId><rank>1000</rank></keyboard>
    </keyboards>
    <timezones>
      <timezone><timezoneId>Europe/Ljubljana</timezoneId><rank>1000</rank></timezone>
    </timezones>
  </language>
  <language>
    <languageId>sq</languageId>
    <iso639-1>sq</iso639-1>
    <iso639-2-t>sqi</iso639-2-t>
    <iso639-2-b>alb</iso639-2-b>
    <names>
      <name><languageId>de</languageId><name>Albanisch</name></name>
      <name><languageId>en</languageId><name>Albanian</name></name>
      <name><languageId>sq</languageId><name>shqip</name></name>
    </names>
    <locales>
      <locale><localeId>sq_AL.UTF-8</localeId><rank>1000</rank></locale>
    </locales>
    <countries>
      <country><countryId>AL</countryId><rank>1000</rank></country>
    </countries>
    <keyboards>
      <keyboard><keyboardId>al</keyboardId><rank>1000</rank></keyboard>
    </keyboards>
    <timezones>
      <timezone><timezoneId>Europe/Tirane</timezoneId><rank>1000</rank></timezone>
    </timezones>
  </language>
  <language>
    <languageId>sr</languageId>
    <iso639-1>sr</iso639-1>
    <iso639-2-t>srp</iso639-2-t>
    <iso639-2-b>srp</iso639-2-b>
    <names>
      <name><languageId>de</languageId><name>Serbisch</name></name>
      <name><languageId>en</languageId><name>Serbian</name></name>
      <name><languageId>sr</languageId><name>Српски</name></name>
      <name><languageId>sr_Latn</languageId><name>Srpski</name></name>
    </names>
    <locales>
      <locale><localeId>sr_RS.UTF-8</localeId><rank>600</rank></locale>
      <locale><localeId>sr_RS.UTF-8@latin</localeId><rank>300</rank></locale>
      <locale><localeId>sr_ME.UTF-8</localeId><rank>100</rank></locale>
    </locales>
    <countries>
      <country><countryId>RS</countryId><rank>900</rank></country>
      <country><countryId>ME</countryId><rank>100</rank></country>
    </countries>
    <keyboards>
      <keyboard><keyboardId>sr</keyboardId><rank>600</rank></keyboard>
      <keyboard><keyboardId>sr(latin)</keyboardId><rank>300</rank></keyboard>
    </keyboards>
    <timezones>
      <timezone><timezoneId>Europe/Belgrade</timezoneId><rank>900</rank></timezone>
      <timezone><timezoneId>Europe/Podgorica</timezoneId><rank>100</rank></timezone>
    </timezones>
  </language>
  <language>
    <languageId>sr_Cyrl</languageId>
    <iso639-1>sr</iso639-1>
    <iso639-2-t>srp</iso639-2-t>
    <iso639-2-b>srp</iso639-2-b>
    <names>
      <name><languageId>de</languageId><name>Serbisch</name></name>
      <name><languageId>en</languageId><name>Serbian</name></name>
      <name><languageId>sr</languageId><name>Српски</name></name>
      <name><languageId>sr_Latn</languageId><name>Srpski</name></name>
    </names>
    <locales>
      <locale><localeId>sr_RS.UTF-8</localeId><rank>600</rank></locale>
      <locale><localeId>sr_ME.UTF-8</localeId><rank>100</rank></locale>
    </locales>
    <countries>
      <country><countryId>RS</countryId><rank>900</rank></country>
      <country><countryId>ME</countryId><rank>100</rank></country>
    </countries>
    <keyboards>
      <keyboard><keyboardId>sr</keyboardId><rank>1000</rank></keyboard>
    </keyboards>
    <timezones>
      <timezone><timezoneId>Europe/Belgrade</timezoneId><rank>900</rank></timezone>
      <timezone><timezoneId>Europe/Podgorica</timezoneId><rank>100</rank></timezone>
    </timezones>
  </language>
  <language>
    <languageId>sr_Latn</languageId>
    <iso639-1>sr</iso639-1>
    <iso639-2-t>srp</iso639-2-t>
    <iso639-2-b>srp</iso639-2-b>
    <names>
      <name><languageId>de</languageId><name>Serbisch</name></name>
      <name><languageId>en</languageId><name>Serbian</name></name>
      <name><languageId>sr</languageId><name>Српски</name></name>
      <name><languageId>sr_Latn</languageId><name>Srpski</name></name>
    </names>
    <locales>
      <locale><localeId>sr_RS.UTF-8@latin</localeId><rank>1000</rank></locale>
      <locale><localeId>sr_ME.UTF-8@latin</localeId><rank>0</rank></locale>
    </locales>
    <countries>
      <country><countryId>RS</countryId><rank>900</rank></country>
      <country><countryId>ME</countryId><rank>100</rank></country>
    </countries>
    <keyboards>
      <keyboard><keyboardId>sr(latin)</keyboardId><rank>300</rank></keyboard>
    </keyboards>
    <timezones>
      <timezone><timezoneId>Europe/Belgrade</timezoneId><rank>900</rank></timezone>
      <timezone><timezoneId>Europe/Podgorica</timezoneId><rank>100</rank></timezone>
    </timezones>
  </language>
  <language>
    <languageId>sv</languageId>
    <iso639-1>sv</iso639-1>
    <iso639-2-t>swe</iso639-2-t>
    <iso639-2-b>swe</iso639-2-b>
    <names>
      <name><languageId>de</languageId><name>Schwedisch</name></name>
      <name><languageId>en</languageId><name>Swedish</name></name>
      <name><languageId>sv</languageId><name>svenska</name></name>
    </names>
    <locales>
      <locale><localeId>sv_SE.UTF-8</localeId><rank>900</rank></locale>
      <locale><localeId>sv_FI.UTF-8</localeId><rank>100</rank></locale>
    </locales>
    <countries>
      <country><countryId>SE</countryId><rank>900</rank></country>
      <country><countryId>FI</countryId><rank>100</rank></country>
    </countries>
    <keyboards>
      <keyboard><keyboardId>se</keyboardId><rank>900</rank></keyboard>
      <keyboard><keyboardId>fi(nodeadkeys)</keyboardId><rank>100</rank></keyboard>
    </keyboards>
    <timezones>
      <timezone><timezoneId>Europe/Stockholm</timezoneId><rank>900</rank></timezone>
      <timezone><timezoneId>Europe/Helsinki</timezoneId><rank>100</rank></timezone>
    </timezones>
  </language>
  <language>
    <languageId>ta</languageId>
    <iso639-1>ta</iso639-1>
    <iso639-2-t>tam</iso639-2-t>
    <iso639-2-b>tam</iso639-2-b>
    <names>
      <name><languageId>de</languageId><name>Tamilisch</name></name>
      <name><languageId>en</languageId><name>Tamil</name></name>
      <name><languageId>ta</languageId><name>தமிழ்</name></name>
    </names>
    <locales>
      <locale><localeId>ta_IN.UTF-8</localeId><rank>700</rank></locale>
      <locale><localeId>ta_LK.UTF-8</localeId><rank>100</rank></locale>
      <locale><localeId>ta_SG.UTF-8</localeId><rank>0</rank></locale>
    </locales>
    <countries>
      <country><countryId>IN</countryId><rank>700</rank></country>
      <country><countryId>LK</countryId><rank>100</rank></country>
      <country><countryId>SG</countryId><rank>50</rank></country>
    </countries>
    <keyboards>
      <keyboard><keyboardId>us</keyboardId><rank>1000</rank></keyboard>
    </keyboards>
    <timezones>
      <timezone><timezoneId>Asia/Kolkata</timezoneId><rank>700</rank></timezone>
      <timezone><timezoneId>Asia/Colombo</timezoneId><rank>100</rank></timezone>
      <timezone><timezoneId>Asia/Singapore</timezoneId><rank>50</rank></timezone>
    </timezones>
  </language>
  <language>
    <languageId>te</languageId>
    <iso639-1>te</iso639-1>
    <iso639-2-t>tel</iso639-2-t>
    <iso639-2-b>tel</iso639-2-b>
    <names>
      <name><languageId>de</languageId><name>Telugu</name></name>
      <name><languageId>en</languageId><name>Telugu</name></name>
      <name><languageId>te</languageId><name>తెలుగు</name></name>
    </names>
    <locales>
      <locale><localeId>te_IN.UTF-8</localeId><rank>1000</rank></locale>
    </locales>
    <countries>
      <country><countryId>IN</countryId><rank>1000</rank></country>
    </countries>
    <keyboards>
      <keyboard><keyboardId>us</keyboardId><rank>1000</rank></keyboard>
    </keyboards>
    <timezones>
      <timezone><timezoneId>Asia/Kolkata</timezoneId><rank>1000</rank></timezone>
    </timezones>
  </language>
  <language>
    <languageId>tr</languageId>
    <iso639-1>tr</iso639-1>
    <iso639-2-t>tur</iso639-2-t>
    <iso639-2-b>tur</iso639-2-b>
    <names>
      <name><languageId>de</languageId><name>Türkisch</name></name>
      <name><languageId>en</languageId><name>Turkish</name></name>
      <name><languageId>tr</languageId><name>Türkçe</name></name>
    </names>
    <locales>
      <locale><localeId>tr_TR.UTF-8</localeId><rank>900</rank></locale>
      <locale><localeId>tr_CY.UTF-8</localeId><rank>100</rank></locale>
    </locales>
    <countries>
      <country><countryId>CY</countryId><rank>900</rank></country>
      <country><countryId>TR</countryId><rank>900</rank></country>
    </countries>
    <keyboards>
      <keyboard><keyboardId>tr</keyboardId><rank>1000</rank></keyboard>
    </keyboards>
    <timezones>
      <timezone><timezoneId>Europe/Istanbul</timezoneId><rank>1000</rank></timezone>
    </timezones>
  </language>
  <language>
    <languageId>uk</languageId>
    <iso639-1>uk</iso639-1>
    <iso639-2-t>ukr</iso639-2-t>
    <iso639-2-b>ukr</iso639-2-b>
    <names>
      <name><languageId>de</languageId><name>Ukrainisch</name></name>
      <name><languageId>en</languageId><name>Ukrainian</name></name>
      <name><languageId>uk</languageId><name>українська</name></name>
    </names>
    <locales>
      <locale><localeId>uk_UA.UTF-8</localeId><rank>1000</rank></locale>
    </locales>
    <countries>
      <country><countryId>UA</countryId><rank>1000</rank></country>
    </countries>
    <keyboards>
      <keyboard><keyboardId>ua</keyboardId><rank>1000</rank></keyboard>
    </keyboards>
    <timezones>
      <timezone><timezoneId>Europe/Kiev</timezoneId><rank>990</rank></timezone>
      <timezone><timezoneId>Europe/Simferopol</timezoneId><rank>1</rank></timezone>
      <timezone><timezoneId>Europe/Zaporozhye</timezoneId><rank>1</rank></timezone>
      <timezone><timezoneId>Europe/Uzhgorod</timezoneId><rank>1</rank></timezone>
    </timezones>
  </language>
  <language>
    <languageId>unm</languageId>
    <iso639-1>None</iso639-1>
    <iso639-2-t>None</iso639-2-t>
    <iso639-2-b>None</iso639-2-b>
    <names>
      <name><languageId>de</languageId><name>Unami Sprache</name></name>
      <name><languageId>en</languageId><name>Unami language</name></name>
      <name><languageId>unm</languageId><name>Lenape</name></name>
    </names>
    <locales>
      <locale><localeId>unm_US.UTF-8</localeId><rank>1000</rank></locale>
    </locales>
    <countries>
      <country><countryId>US</countryId><rank>1000</rank></country>
    </countries>
    <keyboards>
      <keyboard><keyboardId>us</keyboardId><rank>1000</rank></keyboard>
    </keyboards>
    <timezones>
      <timezone><timezoneId>America/Chicago</timezoneId><rank>1000</rank></timezone>
      <timezone><timezoneId>America/New_York</timezoneId><rank>1000</rank></timezone>
    </timezones>
  </language>
  <language>
    <languageId>vi</languageId>
    <iso639-1>vi</iso639-1>
    <iso639-2-t>vie</iso639-2-t>
    <iso639-2-b>vie</iso639-2-b>
    <names>
      <name><languageId>de</languageId><name>Vietnamesisch</name></name>
      <name><languageId>en</languageId><name>Vietnamese</name></name>
      <name><languageId>vi</languageId><name>Tiếng Việt</name></name>
    </names>
    <locales>
      <locale><localeId>vi_VN.UTF-8</localeId><rank>1000</rank></locale>
    </locales>
    <countries>
      <country><countryId>VN</countryId><rank>1000</rank></country>
    </countries>
    <keyboards>
      <keyboard><keyboardId>vn</keyboardId><rank>1000</rank></keyboard>
    </keyboards>
    <timezones>
      <timezone><timezoneId>Asia/Ho_Chi_Minh</timezoneId><rank>1000</rank></timezone>
    </timezones>
  </language>
  <language>
    <languageId>yi</languageId>
    <iso639-1>yi</iso639-1>
    <iso639-2-t>yid</iso639-2-t>
    <iso639-2-b>yid</iso639-2-b>
    <names>
      <name><languageId>de</languageId><name>Jiddisch</name></name>
      <name><languageId>en</languageId><name>Yiddish</name></name>
      <name><languageId>yi</languageId><name>ייִדיש</name></name>
    </names>
    <locales>
      <locale><localeId>yi_US.UTF-8</localeId><rank>1000</rank></locale>
    </locales>
    <countries>
      <country><countryId>US</countryId><rank>1000</rank></country>
    </countries>
    <keyboards>
      <keyboard><keyboardId>us</keyboardId><rank>1000</rank></keyboard>
    </keyboards>
    <timezones>
      <timezone><timezoneId>America/Denver</timezoneId><rank>1000</rank></timezone>
      <timezone><timezoneId>Pacific/Honolulu</timezoneId><rank>1000</rank></timezone>
      <timezone><timezoneId>America/Phoenix</timezoneId><rank>1000</rank></timezone>
      <timezone><timezoneId>America/Chicago</timezoneId><rank>1000</rank></timezone>
      <timezone><timezoneId>America/Los_Angeles</timezoneId><rank>1000</rank></timezone>
      <timezone><timezoneId>America/New_York</timezoneId><rank>1000</rank></timezone>
      <timezone><timezoneId>America/Anchorage</timezoneId><rank>1000</rank></timezone>
      <timezone><timezoneId>America/Metlakatla</timezoneId><rank>1</rank></timezone>
      <timezone><timezoneId>America/Menominee</timezoneId><rank>1</rank></timezone>
      <timezone><timezoneId>America/Indiana/Tell_City</timezoneId><rank>1</rank></timezone>
      <timezone><timezoneId>America/North_Dakota/New_Salem</timezoneId><rank>1</rank></timezone>
      <timezone><timezoneId>America/North_Dakota/Center</timezoneId><rank>1</rank></timezone>
      <timezone><timezoneId>America/Indiana/Vevay</timezoneId><rank>1</rank></timezone>
      <timezone><timezoneId>America/Adak</timezoneId><rank>1</rank></timezone>
      <timezone><timezoneId>America/Indiana/Marengo</timezoneId><rank>1</rank></timezone>
      <timezone><timezoneId>America/Detroit</timezoneId><rank>1</rank></timezone>
      <timezone><timezoneId>America/Indiana/Knox</timezoneId><rank>1</rank></timezone>
      <timezone><timezoneId>America/Shiprock</timezoneId><rank>1</rank></timezone>
      <timezone><timezoneId>America/Indiana/Vincennes</timezoneId><rank>1</rank></timezone>
      <timezone><timezoneId>America/Indiana/Petersburg</timezoneId><rank>1</rank></timezone>
      <timezone><timezoneId>America/Indiana/Indianapolis</timezoneId><rank>1</rank></timezone>
      <timezone><timezoneId>America/Kentucky/Monticello</timezoneId><rank>1</rank></timezone>
      <timezone><timezoneId>America/Nome</timezoneId><rank>1</rank></timezone>
      <timezone><timezoneId>America/Yakutat</timezoneId><rank>1</rank></timezone>
      <timezone><timezoneId>America/North_Dakota/Beulah</timezoneId><rank>1</rank></timezone>
      <timezone><timezoneId>America/Juneau</timezoneId><rank>1</rank></timezone>
      <timezone><timezoneId>America/Sitka</timezoneId><rank>1</rank></timezone>
      <timezone><timezoneId>America/Kentucky/Louisville</timezoneId><rank>1</rank></timezone>
      <timezone><timezoneId>America/Boise</timezoneId><rank>1</rank></timezone>
      <timezone><timezoneId>America/Indiana/Winamac</timezoneId><rank>1</rank></timezone>
    </timezones>
  </language>
  <language>
    <languageId>zh</languageId>
    <iso639-1>zh</iso639-1>
    <iso639-2-t>zho</iso639-2-t>
    <iso639-2-b>chi</iso639-2-b>
    <names>
      <name><languageId>de</languageId><name>Chinesich</name></name>
      <name><languageId>en</languageId><name>Chinese</name></name>
      <name><languageId>zh</languageId><name>中文</name></name>
    </names>
    <locales>
      <locale><localeId>zh_CN.UTF-8</localeId><rank>900</rank></locale>
      <locale><localeId>zh_TW.UTF-8</localeId><rank>20</rank></locale>
      <locale><localeId>zh_HK.UTF-8</localeId><rank>19</rank></locale>
      <locale><localeId>zh_SG.UTF-8</localeId><rank>10</rank></locale>
      <locale><localeId>zh_MO.UTF-8</localeId><rank>0</rank></locale>
    </locales>
    <countries>
      <country><countryId>CN</countryId><rank>900</rank></country>
      <country><countryId>TW</countryId><rank>20</rank></country>
      <country><countryId>HK</countryId><rank>19</rank></country>
      <country><countryId>SG</countryId><rank>10</rank></country>
      <country><countryId>MO</countryId><rank>9</rank></country>
    </countries>
    <keyboards>
      <keyboard><keyboardId>cn</keyboardId><rank>1000</rank></keyboard>
    </keyboards>
    <timezones>
      <timezone><timezoneId>Asia/Shanghai</timezoneId><rank>900</rank></timezone>
      <timezone><timezoneId>Asia/Taipei</timezoneId><rank>20</rank></timezone>
      <timezone><timezoneId>Asia/Hong_Kong</timezoneId><rank>19</rank></timezone>
      <timezone><timezoneId>Asia/Singapore</timezoneId><rank>10</rank></timezone>
      <timezone><timezoneId>Asia/Macau</timezoneId><rank>9</rank></timezone>
    </timezones>
  </language>
  <language>
    <languageId>zh_CN</languageId>
    <iso639-1>zh</iso639-1>
    <iso639-2-t>zho</iso639-2-t>
    <iso639-2-b>chi</iso639-2-b>
    <names>
      <name><languageId>en</languageId><name>Simplified Chinese (China)</name></name>
      <name><languageId>zh_CN</languageId><name>简体中文 (中国)</name></name>
    </names>
    <locales>
      <locale><localeId>zh_CN.UTF-8</localeId><rank>900</rank></locale>
    </locales>
    <countries>
      <country><countryId>CN</countryId><rank>900</rank></country>
    </countries>
    <keyboards>
      <keyboard><keyboardId>cn</keyboardId><rank>1000</rank></keyboard>
    </keyboards>
    <timezones>
      <timezone><timezoneId>Asia/Shanghai</timezoneId><rank>1000</rank></timezone>
    </timezones>
  </language>
  <language>
    <languageId>zh_HK</languageId>
    <iso639-1>zh</iso639-1>
    <iso639-2-t>zho</iso639-2-t>
    <iso639-2-b>chi</iso639-2-b>
    <names>
      <name><languageId>de</languageId><name>Traditionelles Chinesich (Sonderverwaltungszone Hongkong)</name></name>
      <name><languageId>en</languageId><name>Traditional Chinese (Hong Kong)</name></name>
      <name><languageId>zh_HK</languageId><name>繁體中文 (中華人民共和國香港特別行政區)</name></name>
    </names>
    <locales>
      <locale><localeId>zh_HK.UTF-8</localeId><rank>900</rank></locale>
    </locales>
    <countries>
      <country><countryId>HK</countryId><rank>900</rank></country>
    </countries>
    <keyboards>
      <keyboard><keyboardId>cn</keyboardId><rank>1000</rank></keyboard>
    </keyboards>
    <timezones>
      <timezone><timezoneId>Asia/Hong_Kong</timezoneId><rank>20</rank></timezone>
    </timezones>
  </language>
  <language>
    <languageId>zh_Hans</languageId>
    <iso639-1>zh</iso639-1>
    <iso639-2-t>zho</iso639-2-t>
    <iso639-2-b>chi</iso639-2-b>
    <names>
      <name><languageId>de</languageId><name>Vereinfachtes Chinesich</name></name>
      <name><languageId>en</languageId><name>Simplified Chinese</name></name>
      <name><languageId>zh_Hans</languageId><name>简体中文</name></name>
    </names>
    <locales>
      <locale><localeId>zh_CN.UTF-8</localeId><rank>900</rank></locale>
      <locale><localeId>zh_SG.UTF-8</localeId><rank>100</rank></locale>
    </locales>
    <countries>
      <country><countryId>CN</countryId><rank>900</rank></country>
      <country><countryId>SG</countryId><rank>100</rank></country>
    </countries>
    <keyboards>
      <keyboard><keyboardId>cn</keyboardId><rank>1000</rank></keyboard>
    </keyboards>
    <timezones>
      <timezone><timezoneId>Asia/Shanghai</timezoneId><rank>20</rank></timezone>
      <timezone><timezoneId>Asia/Singapore</timezoneId><rank>19</rank></timezone>
    </timezones>
  </language>
  <language>
    <languageId>zh_Hant</languageId>
    <iso639-1>zh</iso639-1>
    <iso639-2-t>zho</iso639-2-t>
    <iso639-2-b>chi</iso639-2-b>
    <names>
      <name><languageId>de</languageId><name>Traditionelles Chinesisch</name></name>
      <name><languageId>en</languageId><name>Traditional Chinese</name></name>
      <name><languageId>zh_Hant</languageId><name>繁體中文</name></name>
    </names>
    <locales>
      <locale><localeId>zh_TW.UTF-8</localeId><rank>20</rank></locale>
      <locale><localeId>zh_HK.UTF-8</localeId><rank>19</rank></locale>
      <locale><localeId>zh_MO.UTF-8</localeId><rank>0</rank></locale>
    </locales>
    <countries>
      <country><countryId>TW</countryId><rank>20</rank></country>
      <country><countryId>HK</countryId><rank>19</rank></country>
      <country><countryId>MO</countryId><rank>9</rank></country>
    </countries>
    <keyboards>
      <keyboard><keyboardId>cn</keyboardId><rank>1000</rank></keyboard>
    </keyboards>
    <timezones>
      <timezone><timezoneId>Asia/Taipei</timezoneId><rank>20</rank></timezone>
      <timezone><timezoneId>Asia/Hong_Kong</timezoneId><rank>19</rank></timezone>
      <timezone><timezoneId>Asia/Macau</timezoneId><rank>9</rank></timezone>
    </timezones>
  </language>
  <language>
    <languageId>zh_MO</languageId>
    <iso639-1>zh</iso639-1>
    <iso639-2-t>zho</iso639-2-t>
    <iso639-2-b>chi</iso639-2-b>
    <names>
      <name><languageId>de</languageId><name>Traditionelles Chinesich (Sonderverwaltungszone Macao)</name></name>
      <name><languageId>en</languageId><name>Traditional Chinese (Macau SAR China)</name></name>
      <name><languageId>zh_MO</languageId><name>繁體中文 (中華人民共和國澳門特別行政區)</name></name>
    </names>
    <locales>
      <locale><localeId>zh_HK.UTF-8</localeId><rank>900</rank></locale>
      <locale><localeId>zh_MO.UTF-8</localeId><rank>0</rank></locale>
    </locales>
    <countries>
      <country><countryId>MO</countryId><rank>900</rank></country>
    </countries>
    <keyboards>
      <keyboard><keyboardId>cn</keyboardId><rank>1000</rank></keyboard>
    </keyboards>
    <timezones>
      <timezone><timezoneId>Asia/Macau</timezoneId><rank>20</rank></timezone>
    </timezones>
  </language>
  <language>
    <languageId>zh_SG</languageId>
    <iso639-1>zh</iso639-1>
    <iso639-2-t>zho</iso639-2-t>
    <iso639-2-b>chi</iso639-2-b>
    <names>
      <name><languageId>de</languageId><name>Vereinfachtes Chinesich (Singapur)</name></name>
      <name><languageId>en</languageId><name>Simplified Chinese (Singapore)</name></name>
      <name><languageId>zh_SG</languageId><name>简体中文 (新加坡)</name></name>
    </names>
    <locales>
      <locale><localeId>zh_SG.UTF-8</localeId><rank>900</rank></locale>
    </locales>
    <countries>
      <country><countryId>SG</countryId><rank>900</rank></country>
    </countries>
    <keyboards>
      <keyboard><keyboardId>cn</keyboardId><rank>1000</rank></keyboard>
    </keyboards>
    <timezones>
      <timezone><timezoneId>Asia/Singapore</timezoneId><rank>1000</rank></timezone>
    </timezones>
  </language>
  <language>
    <languageId>zh_TW</languageId>
    <iso639-1>zh</iso639-1>
    <iso639-2-t>zho</iso639-2-t>
    <iso639-2-b>chi</iso639-2-b>
    <names>
      <name><languageId>de</languageId><name>Traditionelles Chinesich (Taiwan)</name></name>
      <name><languageId>en</languageId><name>Traditional Chinese (Taiwan)</name></name>
      <name><languageId>zh_TW</languageId><name>繁體中文 (台灣)</name></name>
    </names>
    <locales>
      <locale><localeId>zh_TW.UTF-8</localeId><rank>900</rank></locale>
    </locales>
    <countries>
      <country><countryId>TW</countryId><rank>900</rank></country>
    </countries>
    <keyboards>
      <keyboard><keyboardId>cn</keyboardId><rank>1000</rank></keyboard>
    </keyboards>
    <timezones>
      <timezone><timezoneId>Asia/Taipei</timezoneId><rank>20</rank></timezone>
    </timezones>
  </language>
  <language>
    <languageId>zu</languageId>
    <iso639-1>zu</iso639-1>
    <iso639-2-t>zul</iso639-2-t>
    <iso639-2-b>zul</iso639-2-b>
    <names>
      <name><languageId>de</languageId><name>Zulu</name></name>
      <name><languageId>en</languageId><name>Zulu</name></name>
      <name><languageId>zu</languageId><name>isiZulu</name></name>
    </names>
    <locales>
      <locale><localeId>zu_ZA.UTF-8</localeId><rank>1000</rank></locale>
    </locales>
    <countries>
      <country><countryId>ZA</countryId><rank>1000</rank></country>
    </countries>
    <keyboards>
      <keyboard><keyboardId>us</keyboardId><rank>1000</rank></keyboard>
    </keyboards>
    <timezones>
      <timezone><timezoneId>Africa/Johannesburg</timezoneId><rank>1000</rank></timezone>
    </timezones>
  </language>
</languages>
